<?xml version="1.0"?>
<ASAP_Annotations>
<Annotations>
<Annotation Name="_2" Type="Polygon" PartOfGroup="_0" Color="#F4FA58">
			<Coordinates>
				<Coordinate Order="0" X="55020" Y="144734" />
				<Coordinate Order="1" X="55025" Y="144884" />
				<Coordinate Order="2" X="53451" Y="145371" />
				<Coordinate Order="3" X="51991" Y="145821" />
				<Coordinate Order="4" X="50305" Y="146233" />
				<Coordinate Order="5" X="48919" Y="146682" />
				<Coordinate Order="6" X="47608" Y="146832" />
				<Coordinate Order="7" X="46896" Y="147282" />
				<Coordinate Order="8" X="45960" Y="148106" />
				<Coordinate Order="9" X="45248" Y="149080" />
				<Coordinate Order="10" X="44012" Y="150466" />
				<Coordinate Order="11" X="42626" Y="151477" />
				<Coordinate Order="12" X="40566" Y="152825" />
				<Coordinate Order="13" X="39742" Y="153462" />
				<Coordinate Order="14" X="38955" Y="154174" />
				<Coordinate Order="15" X="38019" Y="154698" />
				<Coordinate Order="16" X="37944" Y="155410" />
				<Coordinate Order="17" X="38131" Y="155972" />
				<Coordinate Order="18" X="37982" Y="156534" />
				<Coordinate Order="19" X="37719" Y="157095" />
				<Coordinate Order="20" X="37719" Y="157920" />
				<Coordinate Order="21" X="38881" Y="159268" />
				<Coordinate Order="22" X="39368" Y="159717" />
				<Coordinate Order="23" X="40379" Y="159867" />
				<Coordinate Order="24" X="41278" Y="160092" />
				<Coordinate Order="25" X="41840" Y="160129" />
				<Coordinate Order="26" X="41765" Y="160991" />
				<Coordinate Order="27" X="41465" Y="161890" />
				<Coordinate Order="28" X="41465" Y="162939" />
				<Coordinate Order="29" X="41615" Y="163538" />
				<Coordinate Order="30" X="42289" Y="164137" />
				<Coordinate Order="31" X="43263" Y="164362" />
				<Coordinate Order="32" X="43076" Y="164887" />
				<Coordinate Order="33" X="43226" Y="165598" />
				<Coordinate Order="34" X="43638" Y="166272" />
				<Coordinate Order="35" X="44050" Y="166797" />
				<Coordinate Order="36" X="44217" Y="166926" />
				<Coordinate Order="37" X="44060" Y="167135" />
				<Coordinate Order="38" X="43890" Y="167319" />
				<Coordinate Order="39" X="43641" Y="167541" />
				<Coordinate Order="40" X="43968" Y="167961" />
				<Coordinate Order="41" X="44322" Y="168262" />
				<Coordinate Order="42" X="44506" Y="168419" />
				<Coordinate Order="43" X="44872" Y="168445" />
				<Coordinate Order="44" X="44951" Y="168616" />
				<Coordinate Order="45" X="44951" Y="168865" />
				<Coordinate Order="46" X="45108" Y="169061" />
				<Coordinate Order="47" X="45292" Y="169100" />
				<Coordinate Order="48" X="45449" Y="168996" />
				<Coordinate Order="49" X="45737" Y="169074" />
				<Coordinate Order="50" X="46156" Y="169402" />
				<Coordinate Order="51" X="46418" Y="169179" />
				<Coordinate Order="52" X="46707" Y="168904" />
				<Coordinate Order="53" X="46942" Y="168642" />
				<Coordinate Order="54" X="47139" Y="168602" />
				<Coordinate Order="55" X="47440" Y="168642" />
				<Coordinate Order="56" X="48069" Y="168576" />
				<Coordinate Order="57" X="48436" Y="168589" />
				<Coordinate Order="58" X="48764" Y="168812" />
				<Coordinate Order="59" X="49275" Y="169127" />
				<Coordinate Order="60" X="49733" Y="169362" />
				<Coordinate Order="61" X="49943" Y="169258" />
				<Coordinate Order="62" X="50087" Y="169061" />
				<Coordinate Order="63" X="50454" Y="169074" />
				<Coordinate Order="64" X="50663" Y="168943" />
				<Coordinate Order="65" X="50716" Y="168589" />
				<Coordinate Order="66" X="50952" Y="168340" />
				<Coordinate Order="67" X="51200" Y="167974" />
				<Coordinate Order="68" X="51161" Y="167384" />
				<Coordinate Order="69" X="50925" Y="167030" />
				<Coordinate Order="70" X="51056" Y="166860" />
				<Coordinate Order="71" X="51436" Y="167066" />
				<Coordinate Order="72" X="52004" Y="167350" />
				<Coordinate Order="73" X="52536" Y="167670" />
				<Coordinate Order="74" X="53317" Y="167670" />
				<Coordinate Order="75" X="53725" Y="167545" />
				<Coordinate Order="76" X="54879" Y="167599" />
				<Coordinate Order="77" X="55979" Y="167137" />
				<Coordinate Order="78" X="56156" Y="167066" />
				<Coordinate Order="79" X="56507" Y="166282" />
				<Coordinate Order="80" X="56664" Y="165418" />
				<Coordinate Order="81" X="56782" Y="164751" />
				<Coordinate Order="82" X="56997" Y="163848" />
				<Coordinate Order="83" X="57743" Y="163966" />
				<Coordinate Order="84" X="58332" Y="164358" />
				<Coordinate Order="85" X="58666" Y="165477" />
				<Coordinate Order="86" X="58764" Y="166085" />
				<Coordinate Order="87" X="59510" Y="166321" />
				<Coordinate Order="88" X="60118" Y="166458" />
				<Coordinate Order="89" X="60727" Y="166753" />
				<Coordinate Order="90" X="61237" Y="167145" />
				<Coordinate Order="91" X="61747" Y="167695" />
				<Coordinate Order="92" X="61983" Y="167891" />
				<Coordinate Order="93" X="62016" Y="158162" />
				<Coordinate Order="94" X="52549" Y="158226" />
				<Coordinate Order="95" X="52578" Y="152768" />
				<Coordinate Order="96" X="55258" Y="152925" />
			</Coordinates>
</Annotation>
<Annotation Name="_2" Type="Spline" PartOfGroup="_0" Color="#F4FA58">
			<Coordinates>
				<Coordinate Order="0" X="68673" Y="169079" />
				<Coordinate Order="1" X="69457" Y="169293" />
				<Coordinate Order="2" X="70170" Y="169400" />
				<Coordinate Order="3" X="71026" Y="169507" />
				<Coordinate Order="4" X="71525" Y="169293" />
				<Coordinate Order="5" X="71989" Y="169792" />
				<Coordinate Order="6" X="72524" Y="169970" />
				<Coordinate Order="7" X="73308" Y="170149" />
				<Coordinate Order="8" X="73807" Y="170220" />
				<Coordinate Order="9" X="74413" Y="170291" />
				<Coordinate Order="10" X="75233" Y="170220" />
				<Coordinate Order="11" X="75875" Y="170006" />
				<Coordinate Order="12" X="76517" Y="169792" />
				<Coordinate Order="13" X="76874" Y="169507" />
				<Coordinate Order="14" X="77373" Y="169364" />
				<Coordinate Order="15" X="78300" Y="169293" />
				<Coordinate Order="16" X="79084" Y="169186" />
				<Coordinate Order="17" X="79869" Y="168544" />
				<Coordinate Order="18" X="80154" Y="167902" />
				<Coordinate Order="19" X="80475" Y="167581" />
				<Coordinate Order="20" X="81045" Y="167510" />
				<Coordinate Order="21" X="81794" Y="167403" />
				<Coordinate Order="22" X="82614" Y="167011" />
				<Coordinate Order="23" X="82721" Y="166440" />
				<Coordinate Order="24" X="82792" Y="166084" />
				<Coordinate Order="25" X="83292" Y="165585" />
				<Coordinate Order="26" X="83719" Y="165228" />
				<Coordinate Order="27" X="84254" Y="164658" />
				<Coordinate Order="28" X="84789" Y="164158" />
				<Coordinate Order="29" X="85110" Y="163731" />
				<Coordinate Order="30" X="85502" Y="162946" />
				<Coordinate Order="31" X="85930" Y="161912" />
				<Coordinate Order="32" X="86358" Y="161235" />
				<Coordinate Order="33" X="87035" Y="160807" />
				<Coordinate Order="34" X="87428" Y="160949" />
				<Coordinate Order="35" X="87784" Y="161556" />
				<Coordinate Order="36" X="88569" Y="162090" />
				<Coordinate Order="37" X="89068" Y="162197" />
				<Coordinate Order="38" X="89068" Y="160522" />
				<Coordinate Order="39" X="89032" Y="158133" />
				<Coordinate Order="40" X="89068" Y="156671" />
				<Coordinate Order="41" X="84932" Y="156635" />
				<Coordinate Order="42" X="76874" Y="156742" />
				<Coordinate Order="43" X="76874" Y="158026" />
				<Coordinate Order="44" X="75483" Y="158133" />
				<Coordinate Order="45" X="75376" Y="160807" />
				<Coordinate Order="46" X="70099" Y="160878" />
				<Coordinate Order="47" X="70063" Y="162197" />
				<Coordinate Order="48" X="68637" Y="162197" />
			</Coordinates>
</Annotation>
<Annotation Name="_2" Type="Polygon" PartOfGroup="_0" Color="#F4FA58">
			<Coordinates>
				<Coordinate Order="0" X="89371" Y="158048" />
				<Coordinate Order="1" X="93313" Y="158124" />
				<Coordinate Order="2" X="94071" Y="156532" />
				<Coordinate Order="3" X="94374" Y="155016" />
				<Coordinate Order="4" X="95208" Y="153954" />
				<Coordinate Order="5" X="95587" Y="152742" />
				<Coordinate Order="6" X="95890" Y="151984" />
				<Coordinate Order="7" X="95511" Y="150619" />
				<Coordinate Order="8" X="95435" Y="149785" />
				<Coordinate Order="9" X="95738" Y="148345" />
				<Coordinate Order="10" X="96648" Y="146905" />
				<Coordinate Order="11" X="96800" Y="145313" />
				<Coordinate Order="12" X="96496" Y="143797" />
				<Coordinate Order="13" X="96572" Y="142812" />
				<Coordinate Order="14" X="96800" Y="141220" />
				<Coordinate Order="15" X="96193" Y="138567" />
				<Coordinate Order="16" X="94222" Y="137354" />
				<Coordinate Order="17" X="92176" Y="138642" />
				<Coordinate Order="18" X="91645" Y="137581" />
				<Coordinate Order="19" X="91039" Y="136217" />
				<Coordinate Order="20" X="90356" Y="135080" />
				<Coordinate Order="21" X="89977" Y="133564" />
				<Coordinate Order="22" X="89522" Y="131593" />
				<Coordinate Order="23" X="88840" Y="130153" />
				<Coordinate Order="24" X="87703" Y="129091" />
				<Coordinate Order="25" X="84823" Y="128333" />
				<Coordinate Order="26" X="84899" Y="129698" />
				<Coordinate Order="27" X="86036" Y="129774" />
				<Coordinate Order="28" X="86263" Y="140386" />
				<Coordinate Order="29" X="83610" Y="140462" />
				<Coordinate Order="30" X="83458" Y="151226" />
				<Coordinate Order="31" X="84671" Y="151301" />
				<Coordinate Order="32" X="84823" Y="156153" />
				<Coordinate Order="33" X="89295" Y="156304" />
			</Coordinates>
</Annotation>
<Annotation Name="_2" Type="Polygon" PartOfGroup="_0" Color="#F4FA58">
			<Coordinates>
				<Coordinate Order="0" X="96681" Y="137072" />
				<Coordinate Order="1" X="96003" Y="136770" />
				<Coordinate Order="2" X="95702" Y="137298" />
				<Coordinate Order="3" X="94722" Y="137298" />
				<Coordinate Order="4" X="93366" Y="136921" />
				<Coordinate Order="5" X="92386" Y="136092" />
				<Coordinate Order="6" X="91105" Y="135113" />
				<Coordinate Order="7" X="90276" Y="133982" />
				<Coordinate Order="8" X="91180" Y="133681" />
				<Coordinate Order="9" X="91331" Y="132098" />
				<Coordinate Order="10" X="91180" Y="131269" />
				<Coordinate Order="11" X="90577" Y="130516" />
				<Coordinate Order="12" X="89975" Y="130064" />
				<Coordinate Order="13" X="90125" Y="129009" />
				<Coordinate Order="14" X="90276" Y="127577" />
				<Coordinate Order="15" X="90125" Y="126070" />
				<Coordinate Order="16" X="89975" Y="124487" />
				<Coordinate Order="17" X="89447" Y="123432" />
				<Coordinate Order="18" X="88392" Y="122302" />
				<Coordinate Order="19" X="87714" Y="120569" />
				<Coordinate Order="20" X="88015" Y="119514" />
				<Coordinate Order="21" X="88392" Y="117555" />
				<Coordinate Order="22" X="89221" Y="117103" />
				<Coordinate Order="23" X="89296" Y="116349" />
				<Coordinate Order="24" X="89975" Y="115897" />
				<Coordinate Order="25" X="90427" Y="115746" />
				<Coordinate Order="26" X="91331" Y="116198" />
				<Coordinate Order="27" X="92009" Y="116274" />
				<Coordinate Order="28" X="92763" Y="115972" />
				<Coordinate Order="29" X="93818" Y="114767" />
				<Coordinate Order="30" X="94496" Y="114088" />
				<Coordinate Order="31" X="95551" Y="113938" />
				<Coordinate Order="32" X="96606" Y="114616" />
				<Coordinate Order="33" X="96907" Y="115595" />
				<Coordinate Order="34" X="95777" Y="116575" />
				<Coordinate Order="35" X="95400" Y="118911" />
				<Coordinate Order="36" X="95099" Y="119514" />
				<Coordinate Order="37" X="94797" Y="120268" />
				<Coordinate Order="38" X="94119" Y="121473" />
				<Coordinate Order="39" X="94044" Y="122378" />
				<Coordinate Order="40" X="93516" Y="124035" />
				<Coordinate Order="41" X="93290" Y="124864" />
				<Coordinate Order="42" X="93290" Y="125995" />
				<Coordinate Order="43" X="93290" Y="126748" />
				<Coordinate Order="44" X="93290" Y="127728" />
				<Coordinate Order="45" X="93441" Y="128858" />
				<Coordinate Order="46" X="93742" Y="129913" />
				<Coordinate Order="47" X="94044" Y="130893" />
				<Coordinate Order="48" X="94571" Y="132098" />
				<Coordinate Order="49" X="95249" Y="133078" />
				<Coordinate Order="50" X="96229" Y="134058" />
				<Coordinate Order="51" X="96757" Y="133982" />
			</Coordinates>
</Annotation>
<Annotation Name="_2" Type="Spline" PartOfGroup="_0" Color="#F4FA58">
			<Coordinates>
				<Coordinate Order="0" X="96898" Y="125303" />
				<Coordinate Order="1" X="97022" Y="130766" />
				<Coordinate Order="2" X="96764" Y="130251" />
				<Coordinate Order="3" X="96721" Y="129864" />
				<Coordinate Order="4" X="96506" Y="129090" />
				<Coordinate Order="5" X="96291" Y="128402" />
				<Coordinate Order="6" X="95990" Y="127542" />
				<Coordinate Order="7" X="95861" Y="127026" />
				<Coordinate Order="8" X="95646" Y="126511" />
				<Coordinate Order="9" X="95388" Y="125823" />
				<Coordinate Order="10" X="95732" Y="125221" />
				<Coordinate Order="11" X="96162" Y="124619" />
				<Coordinate Order="12" X="96248" Y="124361" />
				<Coordinate Order="13" X="96461" Y="124456" />
				<Coordinate Order="14" X="96542" Y="124725" />
				<Coordinate Order="15" X="96757" Y="125048" />
			</Coordinates>
</Annotation>
<Annotation Name="_2" Type="Polygon" PartOfGroup="_0" Color="#F4FA58">
			<Coordinates>
				<Coordinate Order="0" X="37620" Y="147566" />
				<Coordinate Order="1" X="37615" Y="147688" />
				<Coordinate Order="2" X="36976" Y="148608" />
				<Coordinate Order="3" X="36452" Y="149413" />
				<Coordinate Order="4" X="35967" Y="150269" />
				<Coordinate Order="5" X="35635" Y="150907" />
				<Coordinate Order="6" X="35213" Y="152019" />
				<Coordinate Order="7" X="35328" Y="152965" />
				<Coordinate Order="8" X="35059" Y="154276" />
				<Coordinate Order="9" X="30611" Y="154363" />
				<Coordinate Order="10" X="30524" Y="153811" />
				<Coordinate Order="11" X="29623" Y="153666" />
				<Coordinate Order="12" X="29041" Y="153142" />
				<Coordinate Order="13" X="28547" Y="152096" />
				<Coordinate Order="14" X="28402" Y="150875" />
				<Coordinate Order="15" X="28634" Y="149799" />
				<Coordinate Order="16" X="29041" Y="149479" />
				<Coordinate Order="17" X="29361" Y="149712" />
				<Coordinate Order="18" X="29797" Y="149538" />
				<Coordinate Order="19" X="30146" Y="148927" />
				<Coordinate Order="20" X="30204" Y="148200" />
				<Coordinate Order="21" X="30582" Y="147735" />
				<Coordinate Order="22" X="31192" Y="147910" />
				<Coordinate Order="23" X="31803" Y="148491" />
				<Coordinate Order="24" X="32297" Y="147445" />
				<Coordinate Order="25" X="33053" Y="146456" />
				<Coordinate Order="26" X="32762" Y="146049" />
				<Coordinate Order="27" X="32995" Y="145352" />
				<Coordinate Order="28" X="33053" Y="144189" />
				<Coordinate Order="29" X="33576" Y="144508" />
				<Coordinate Order="30" X="33663" Y="144043" />
				<Coordinate Order="31" X="33576" Y="143288" />
				<Coordinate Order="32" X="32937" Y="143607" />
				<Coordinate Order="33" X="32355" Y="144131" />
				<Coordinate Order="34" X="31658" Y="144043" />
				<Coordinate Order="35" X="31628" Y="143491" />
				<Coordinate Order="36" X="31919" Y="142793" />
				<Coordinate Order="37" X="31948" Y="142212" />
				<Coordinate Order="38" X="31599" Y="141572" />
				<Coordinate Order="39" X="31251" Y="141340" />
				<Coordinate Order="40" X="31575" Y="140197" />
				<Coordinate Order="41" X="31981" Y="139760" />
				<Coordinate Order="42" X="32074" Y="139010" />
				<Coordinate Order="43" X="32137" Y="138198" />
				<Coordinate Order="44" X="32449" Y="138198" />
				<Coordinate Order="45" X="32762" Y="138198" />
				<Coordinate Order="46" X="33449" Y="137948" />
				<Coordinate Order="47" X="33823" Y="137948" />
				<Coordinate Order="48" X="34261" Y="137948" />
				<Coordinate Order="49" X="34417" Y="137730" />
				<Coordinate Order="50" X="34573" Y="137199" />
				<Coordinate Order="51" X="34792" Y="137074" />
				<Coordinate Order="52" X="35135" Y="137324" />
				<Coordinate Order="53" X="35229" Y="137574" />
				<Coordinate Order="54" X="35135" Y="137886" />
				<Coordinate Order="55" X="35135" Y="138198" />
				<Coordinate Order="56" X="35354" Y="138386" />
				<Coordinate Order="57" X="35947" Y="138698" />
				<Coordinate Order="58" X="36259" Y="139042" />
				<Coordinate Order="59" X="36541" Y="139510" />
				<Coordinate Order="60" X="36790" Y="139885" />
				<Coordinate Order="61" X="36853" Y="140790" />
				<Coordinate Order="62" X="36915" Y="141384" />
				<Coordinate Order="63" X="36947" Y="141946" />
				<Coordinate Order="64" X="36790" Y="142508" />
				<Coordinate Order="65" X="36728" Y="143164" />
				<Coordinate Order="66" X="36853" Y="143695" />
				<Coordinate Order="67" X="36853" Y="144163" />
				<Coordinate Order="68" X="36915" Y="144632" />
				<Coordinate Order="69" X="36947" Y="145132" />
				<Coordinate Order="70" X="37071" Y="145506" />
				<Coordinate Order="71" X="37165" Y="146069" />
				<Coordinate Order="72" X="37228" Y="146475" />
				<Coordinate Order="73" X="37321" Y="146849" />
				<Coordinate Order="74" X="37509" Y="146943" />
				<Coordinate Order="75" X="37634" Y="147193" />
			</Coordinates>
</Annotation>
<Annotation Name="_2" Type="Polygon" PartOfGroup="_0" Color="#F4FA58">
			<Coordinates>
				<Coordinate Order="0" X="8723" Y="135806" />
				<Coordinate Order="1" X="8757" Y="134516" />
				<Coordinate Order="2" X="9199" Y="133294" />
				<Coordinate Order="3" X="9029" Y="132819" />
				<Coordinate Order="4" X="8078" Y="133023" />
				<Coordinate Order="5" X="7739" Y="133430" />
				<Coordinate Order="6" X="7434" Y="132514" />
				<Coordinate Order="7" X="7196" Y="131326" />
				<Coordinate Order="8" X="7535" Y="130036" />
				<Coordinate Order="9" X="7671" Y="129255" />
				<Coordinate Order="10" X="7671" Y="128610" />
				<Coordinate Order="11" X="7875" Y="127796" />
				<Coordinate Order="12" X="8011" Y="126302" />
				<Coordinate Order="13" X="8486" Y="125488" />
				<Coordinate Order="14" X="8689" Y="124741" />
				<Coordinate Order="15" X="8893" Y="123858" />
				<Coordinate Order="16" X="9402" Y="123281" />
				<Coordinate Order="17" X="9911" Y="122636" />
				<Coordinate Order="18" X="10522" Y="121957" />
				<Coordinate Order="19" X="11269" Y="121516" />
				<Coordinate Order="20" X="11609" Y="121347" />
				<Coordinate Order="21" X="11948" Y="121516" />
				<Coordinate Order="22" X="12321" Y="121720" />
				<Coordinate Order="23" X="13543" Y="121550" />
				<Coordinate Order="24" X="14256" Y="121618" />
				<Coordinate Order="25" X="14765" Y="122093" />
				<Coordinate Order="26" X="14731" Y="122670" />
				<Coordinate Order="27" X="15173" Y="122942" />
				<Coordinate Order="28" X="15919" Y="123044" />
				<Coordinate Order="29" X="16564" Y="123451" />
				<Coordinate Order="30" X="16972" Y="123960" />
				<Coordinate Order="31" X="16700" Y="124571" />
				<Coordinate Order="32" X="17039" Y="124877" />
				<Coordinate Order="33" X="17549" Y="124944" />
				<Coordinate Order="34" X="17820" Y="125352" />
				<Coordinate Order="35" X="17990" Y="124300" />
				<Coordinate Order="36" X="17616" Y="123790" />
				<Coordinate Order="37" X="17243" Y="122297" />
				<Coordinate Order="38" X="17616" Y="121482" />
				<Coordinate Order="39" X="18567" Y="121109" />
				<Coordinate Order="40" X="19585" Y="120973" />
				<Coordinate Order="41" X="20603" Y="121279" />
				<Coordinate Order="42" X="21418" Y="121686" />
				<Coordinate Order="43" X="22199" Y="122399" />
				<Coordinate Order="44" X="22301" Y="122976" />
				<Coordinate Order="45" X="22335" Y="123858" />
				<Coordinate Order="46" X="23556" Y="123790" />
				<Coordinate Order="47" X="24846" Y="123553" />
				<Coordinate Order="48" X="26340" Y="123281" />
				<Coordinate Order="49" X="27969" Y="123145" />
				<Coordinate Order="50" X="28207" Y="123145" />
				<Coordinate Order="51" X="27731" Y="123519" />
				<Coordinate Order="52" X="27426" Y="123655" />
				<Coordinate Order="53" X="27154" Y="123858" />
				<Coordinate Order="54" X="26951" Y="124130" />
				<Coordinate Order="55" X="26611" Y="124266" />
				<Coordinate Order="56" X="26340" Y="124469" />
				<Coordinate Order="57" X="25831" Y="124435" />
				<Coordinate Order="58" X="25525" Y="124435" />
				<Coordinate Order="59" X="24914" Y="124503" />
				<Coordinate Order="60" X="24541" Y="124537" />
				<Coordinate Order="61" X="24167" Y="124775" />
				<Coordinate Order="62" X="23930" Y="124944" />
				<Coordinate Order="63" X="23692" Y="125454" />
				<Coordinate Order="64" X="23624" Y="125759" />
				<Coordinate Order="65" X="23251" Y="125861" />
				<Coordinate Order="66" X="23013" Y="125997" />
				<Coordinate Order="67" X="22640" Y="126336" />
				<Coordinate Order="68" X="22301" Y="126574" />
				<Coordinate Order="69" X="21995" Y="126913" />
				<Coordinate Order="70" X="21825" Y="126981" />
				<Coordinate Order="71" X="21486" Y="126981" />
				<Coordinate Order="72" X="21248" Y="126879" />
				<Coordinate Order="73" X="21011" Y="126811" />
				<Coordinate Order="74" X="20773" Y="126710" />
				<Coordinate Order="75" X="20502" Y="126710" />
				<Coordinate Order="76" X="20128" Y="126777" />
				<Coordinate Order="77" X="19823" Y="126879" />
				<Coordinate Order="78" X="19551" Y="127049" />
				<Coordinate Order="79" X="19348" Y="127083" />
				<Coordinate Order="80" X="19144" Y="127117" />
				<Coordinate Order="81" X="18737" Y="126811" />
				<Coordinate Order="82" X="18261" Y="126981" />
				<Coordinate Order="83" X="17990" Y="127049" />
				<Coordinate Order="84" X="17752" Y="127253" />
				<Coordinate Order="85" X="17345" Y="127626" />
				<Coordinate Order="86" X="17209" Y="127931" />
				<Coordinate Order="87" X="17447" Y="128203" />
				<Coordinate Order="88" X="17379" Y="128610" />
				<Coordinate Order="89" X="17005" Y="128746" />
				<Coordinate Order="90" X="16632" Y="129018" />
				<Coordinate Order="91" X="16293" Y="129357" />
				<Coordinate Order="92" X="16293" Y="129697" />
				<Coordinate Order="93" X="16564" Y="129968" />
				<Coordinate Order="94" X="16564" Y="130206" />
				<Coordinate Order="95" X="16564" Y="130307" />
				<Coordinate Order="96" X="15987" Y="130579" />
				<Coordinate Order="97" X="15817" Y="130851" />
				<Coordinate Order="98" X="15478" Y="130681" />
				<Coordinate Order="99" X="15071" Y="130613" />
				<Coordinate Order="100" X="14867" Y="130545" />
				<Coordinate Order="101" X="14426" Y="130715" />
				<Coordinate Order="102" X="14222" Y="130579" />
				<Coordinate Order="103" X="13951" Y="130443" />
				<Coordinate Order="104" X="13713" Y="130409" />
				<Coordinate Order="105" X="13509" Y="130375" />
				<Coordinate Order="106" X="13170" Y="130443" />
				<Coordinate Order="107" X="12966" Y="130579" />
				<Coordinate Order="108" X="12763" Y="130783" />
				<Coordinate Order="109" X="12593" Y="131156" />
				<Coordinate Order="110" X="12559" Y="131394" />
				<Coordinate Order="111" X="12491" Y="131665" />
				<Coordinate Order="112" X="12355" Y="131903" />
				<Coordinate Order="113" X="11982" Y="132140" />
				<Coordinate Order="114" X="11710" Y="132174" />
				<Coordinate Order="115" X="11269" Y="132412" />
				<Coordinate Order="116" X="10930" Y="132446" />
				<Coordinate Order="117" X="10794" Y="132616" />
				<Coordinate Order="118" X="10522" Y="132616" />
				<Coordinate Order="119" X="10353" Y="133057" />
				<Coordinate Order="120" X="10115" Y="133328" />
				<Coordinate Order="121" X="10013" Y="133702" />
				<Coordinate Order="122" X="9810" Y="134109" />
				<Coordinate Order="123" X="9674" Y="134381" />
				<Coordinate Order="124" X="9470" Y="134720" />
				<Coordinate Order="125" X="9300" Y="135127" />
				<Coordinate Order="126" X="8893" Y="135399" />
			</Coordinates>
</Annotation>
<Annotation Name="_2" Type="Polygon" PartOfGroup="_0" Color="#F4FA58">
			<Coordinates>
				<Coordinate Order="0" X="30434" Y="98623" />
				<Coordinate Order="1" X="30366" Y="104249" />
				<Coordinate Order="2" X="41076" Y="104385" />
				<Coordinate Order="3" X="47312" Y="104656" />
				<Coordinate Order="4" X="47109" Y="103571" />
				<Coordinate Order="5" X="47134" Y="103252" />
				<Coordinate Order="6" X="46813" Y="103064" />
				<Coordinate Order="7" X="46519" Y="102931" />
				<Coordinate Order="8" X="46199" Y="102824" />
				<Coordinate Order="9" X="46065" Y="102610" />
				<Coordinate Order="10" X="46359" Y="102343" />
				<Coordinate Order="11" X="46573" Y="101835" />
				<Coordinate Order="12" X="47001" Y="101567" />
				<Coordinate Order="13" X="46787" Y="101273" />
				<Coordinate Order="14" X="46573" Y="101033" />
				<Coordinate Order="15" X="46626" Y="100765" />
				<Coordinate Order="16" X="46600" Y="100498" />
				<Coordinate Order="17" X="46813" Y="100391" />
				<Coordinate Order="18" X="46974" Y="100150" />
				<Coordinate Order="19" X="47268" Y="99990" />
				<Coordinate Order="20" X="47482" Y="99856" />
				<Coordinate Order="21" X="47803" Y="99589" />
				<Coordinate Order="22" X="48017" Y="99455" />
				<Coordinate Order="23" X="48070" Y="99215" />
				<Coordinate Order="24" X="48230" Y="99054" />
				<Coordinate Order="25" X="48444" Y="98787" />
				<Coordinate Order="26" X="48605" Y="98573" />
				<Coordinate Order="27" X="48979" Y="98466" />
				<Coordinate Order="28" X="49246" Y="98306" />
				<Coordinate Order="29" X="49674" Y="98092" />
				<Coordinate Order="30" X="49968" Y="97931" />
				<Coordinate Order="31" X="50209" Y="97717" />
				<Coordinate Order="32" X="50556" Y="97584" />
				<Coordinate Order="33" X="50850" Y="97370" />
				<Coordinate Order="34" X="51225" Y="97236" />
				<Coordinate Order="35" X="51492" Y="97156" />
				<Coordinate Order="36" X="51813" Y="96969" />
				<Coordinate Order="37" X="52054" Y="97022" />
				<Coordinate Order="38" X="52321" Y="96969" />
				<Coordinate Order="39" X="52722" Y="96996" />
				<Coordinate Order="40" X="53123" Y="96996" />
				<Coordinate Order="41" X="53639" Y="96721" />
				<Coordinate Order="42" X="54352" Y="96721" />
				<Coordinate Order="43" X="55578" Y="97146" />
				<Coordinate Order="44" X="56623" Y="96928" />
				<Coordinate Order="45" X="56777" Y="96293" />
				<Coordinate Order="46" X="57348" Y="85736" />
				<Coordinate Order="47" X="57040" Y="84370" />
				<Coordinate Order="48" X="56360" Y="83010" />
				<Coordinate Order="49" X="55952" Y="81786" />
				<Coordinate Order="50" X="54728" Y="81242" />
				<Coordinate Order="51" X="53057" Y="81718" />
				<Coordinate Order="52" X="52599" Y="82087" />
				<Coordinate Order="53" X="52089" Y="82246" />
				<Coordinate Order="54" X="51736" Y="82581" />
				<Coordinate Order="55" X="51736" Y="82845" />
				<Coordinate Order="56" X="51454" Y="83074" />
				<Coordinate Order="57" X="51261" Y="83409" />
				<Coordinate Order="58" X="51384" Y="83620" />
				<Coordinate Order="59" X="51507" Y="83884" />
				<Coordinate Order="60" X="51560" Y="84096" />
				<Coordinate Order="61" X="51313" Y="84413" />
				<Coordinate Order="62" X="51120" Y="84659" />
				<Coordinate Order="63" X="50891" Y="84941" />
				<Coordinate Order="64" X="50697" Y="85188" />
				<Coordinate Order="65" X="50415" Y="85558" />
				<Coordinate Order="66" X="50028" Y="85892" />
				<Coordinate Order="67" X="49393" Y="85998" />
				<Coordinate Order="68" X="48565" Y="85910" />
				<Coordinate Order="69" X="47878" Y="86157" />
				<Coordinate Order="70" X="46487" Y="86174" />
				<Coordinate Order="71" X="46346" Y="87161" />
				<Coordinate Order="72" X="46553" Y="87458" />
				<Coordinate Order="73" X="46421" Y="87750" />
				<Coordinate Order="74" X="46328" Y="88082" />
				<Coordinate Order="75" X="46660" Y="88413" />
				<Coordinate Order="76" X="46756" Y="89182" />
				<Coordinate Order="77" X="46873" Y="89650" />
				<Coordinate Order="78" X="47253" Y="89942" />
				<Coordinate Order="79" X="47634" Y="90206" />
				<Coordinate Order="80" X="47809" Y="90440" />
				<Coordinate Order="81" X="47312" Y="90498" />
				<Coordinate Order="82" X="46697" Y="90323" />
				<Coordinate Order="83" X="46171" Y="90645" />
				<Coordinate Order="84" X="45527" Y="90615" />
				<Coordinate Order="85" X="45147" Y="90293" />
				<Coordinate Order="86" X="44474" Y="90264" />
				<Coordinate Order="87" X="43567" Y="90498" />
				<Coordinate Order="88" X="43186" Y="90791" />
				<Coordinate Order="89" X="42835" Y="90791" />
				<Coordinate Order="90" X="42133" Y="90849" />
				<Coordinate Order="91" X="41899" Y="90674" />
				<Coordinate Order="92" X="41489" Y="90498" />
				<Coordinate Order="93" X="40875" Y="90410" />
				<Coordinate Order="94" X="40260" Y="90645" />
				<Coordinate Order="95" X="39968" Y="90996" />
				<Coordinate Order="96" X="40026" Y="91639" />
				<Coordinate Order="97" X="40085" Y="91961" />
				<Coordinate Order="98" X="39334" Y="92626" />
				<Coordinate Order="99" X="38784" Y="93937" />
				<Coordinate Order="100" X="38150" Y="94741" />
				<Coordinate Order="101" X="37981" Y="95417" />
				<Coordinate Order="102" X="37262" Y="96009" />
				<Coordinate Order="103" X="36543" Y="96052" />
				<Coordinate Order="104" X="36289" Y="96136" />
				<Coordinate Order="105" X="35824" Y="96686" />
				<Coordinate Order="106" X="35781" Y="97321" />
				<Coordinate Order="107" X="35232" Y="97490" />
				<Coordinate Order="108" X="34640" Y="97617" />
				<Coordinate Order="109" X="34174" Y="97236" />
				<Coordinate Order="110" X="33963" Y="96602" />
				<Coordinate Order="111" X="33624" Y="96094" />
				<Coordinate Order="112" X="33328" Y="96348" />
				<Coordinate Order="113" X="32948" Y="96855" />
				<Coordinate Order="114" X="32652" Y="97574" />
				<Coordinate Order="115" X="32652" Y="98124" />
				<Coordinate Order="116" X="32609" Y="98420" />
				<Coordinate Order="117" X="32017" Y="98463" />
				<Coordinate Order="118" X="31171" Y="98716" />
			</Coordinates>
</Annotation>
<Annotation Name="_2" Type="Polygon" PartOfGroup="_0" Color="#F4FA58">
			<Coordinates>
				<Coordinate Order="0" X="57522" Y="85885" />
				<Coordinate Order="1" X="56840" Y="96829" />
				<Coordinate Order="2" X="57559" Y="96791" />
				<Coordinate Order="3" X="58658" Y="96866" />
				<Coordinate Order="4" X="59491" Y="97018" />
				<Coordinate Order="5" X="60210" Y="97018" />
				<Coordinate Order="6" X="60702" Y="97018" />
				<Coordinate Order="7" X="61081" Y="97094" />
				<Coordinate Order="8" X="61990" Y="97548" />
				<Coordinate Order="9" X="62444" Y="97586" />
				<Coordinate Order="10" X="62937" Y="97775" />
				<Coordinate Order="11" X="63315" Y="97927" />
				<Coordinate Order="12" X="63618" Y="98078" />
				<Coordinate Order="13" X="63883" Y="98230" />
				<Coordinate Order="14" X="64186" Y="98381" />
				<Coordinate Order="15" X="64489" Y="98608" />
				<Coordinate Order="16" X="64830" Y="99025" />
				<Coordinate Order="17" X="65322" Y="99366" />
				<Coordinate Order="18" X="65701" Y="99820" />
				<Coordinate Order="19" X="66080" Y="100350" />
				<Coordinate Order="20" X="66534" Y="101070" />
				<Coordinate Order="21" X="66458" Y="101789" />
				<Coordinate Order="22" X="73464" Y="102244" />
				<Coordinate Order="23" X="74411" Y="101486" />
				<Coordinate Order="24" X="75017" Y="101032" />
				<Coordinate Order="25" X="75736" Y="100047" />
				<Coordinate Order="26" X="75888" Y="99025" />
				<Coordinate Order="27" X="75698" Y="97927" />
				<Coordinate Order="28" X="75395" Y="97056" />
				<Coordinate Order="29" X="74714" Y="96336" />
				<Coordinate Order="30" X="74146" Y="95655" />
				<Coordinate Order="31" X="73540" Y="94746" />
				<Coordinate Order="32" X="72972" Y="94026" />
				<Coordinate Order="33" X="72820" Y="93307" />
				<Coordinate Order="34" X="72593" Y="92777" />
				<Coordinate Order="35" X="72063" Y="92209" />
				<Coordinate Order="36" X="71608" Y="91868" />
				<Coordinate Order="37" X="70927" Y="91186" />
				<Coordinate Order="38" X="70548" Y="90656" />
				<Coordinate Order="39" X="70245" Y="90088" />
				<Coordinate Order="40" X="69223" Y="89444" />
				<Coordinate Order="41" X="68579" Y="89066" />
				<Coordinate Order="42" X="68011" Y="89028" />
				<Coordinate Order="43" X="67367" Y="88763" />
				<Coordinate Order="44" X="66761" Y="88081" />
				<Coordinate Order="45" X="66307" Y="87172" />
				<Coordinate Order="46" X="65777" Y="86263" />
				<Coordinate Order="47" X="64830" Y="85430" />
				<Coordinate Order="48" X="63543" Y="84900" />
				<Coordinate Order="49" X="62369" Y="84749" />
				<Coordinate Order="50" X="61233" Y="84446" />
				<Coordinate Order="51" X="60059" Y="84067" />
				<Coordinate Order="52" X="57900" Y="84370" />
				<Coordinate Order="53" X="57332" Y="84711" />
			</Coordinates>
</Annotation>
<Annotation Name="_2" Type="Polygon" PartOfGroup="_0" Color="#F4FA58">
			<Coordinates>
				<Coordinate Order="0" X="74304" Y="106390" />
				<Coordinate Order="1" X="73852" Y="113546" />
				<Coordinate Order="2" X="73852" Y="116332" />
				<Coordinate Order="3" X="75132" Y="116408" />
				<Coordinate Order="4" X="75207" Y="117575" />
				<Coordinate Order="5" X="76563" Y="117726" />
				<Coordinate Order="6" X="76601" Y="120324" />
				<Coordinate Order="7" X="80593" Y="120362" />
				<Coordinate Order="8" X="80969" Y="121416" />
				<Coordinate Order="9" X="81421" Y="121228" />
				<Coordinate Order="10" X="82250" Y="121379" />
				<Coordinate Order="11" X="83229" Y="121755" />
				<Coordinate Order="12" X="84472" Y="121718" />
				<Coordinate Order="13" X="85790" Y="121078" />
				<Coordinate Order="14" X="86618" Y="120249" />
				<Coordinate Order="15" X="87146" Y="119571" />
				<Coordinate Order="16" X="87711" Y="119646" />
				<Coordinate Order="17" X="88200" Y="117312" />
				<Coordinate Order="18" X="88087" Y="117010" />
				<Coordinate Order="19" X="86957" Y="116634" />
				<Coordinate Order="20" X="85941" Y="116634" />
				<Coordinate Order="21" X="85037" Y="116634" />
				<Coordinate Order="22" X="84058" Y="116784" />
				<Coordinate Order="23" X="83229" Y="116747" />
				<Coordinate Order="24" X="82401" Y="116784" />
				<Coordinate Order="25" X="82099" Y="116483" />
				<Coordinate Order="26" X="81685" Y="115956" />
				<Coordinate Order="27" X="81271" Y="115240" />
				<Coordinate Order="28" X="80743" Y="114751" />
				<Coordinate Order="29" X="80442" Y="114412" />
				<Coordinate Order="30" X="79877" Y="113771" />
				<Coordinate Order="31" X="79576" Y="113395" />
				<Coordinate Order="32" X="79162" Y="113018" />
				<Coordinate Order="33" X="78823" Y="112453" />
				<Coordinate Order="34" X="78635" Y="112001" />
				<Coordinate Order="35" X="78559" Y="111550" />
				<Coordinate Order="36" X="78409" Y="111135" />
				<Coordinate Order="37" X="78183" Y="110759" />
				<Coordinate Order="38" X="78032" Y="110194" />
				<Coordinate Order="39" X="77844" Y="109780" />
				<Coordinate Order="40" X="77693" Y="109290" />
				<Coordinate Order="41" X="77429" Y="108574" />
				<Coordinate Order="42" X="77128" Y="108047" />
				<Coordinate Order="43" X="76864" Y="107595" />
				<Coordinate Order="44" X="76601" Y="106842" />
				<Coordinate Order="45" X="76300" Y="106428" />
				<Coordinate Order="46" X="75697" Y="106315" />
				<Coordinate Order="47" X="74944" Y="106465" />
			</Coordinates>
</Annotation>
<Annotation Name="_2" Type="Polygon" PartOfGroup="_0" Color="#F4FA58">
			<Coordinates>
				<Coordinate Order="0" X="67110" Y="103453" />
				<Coordinate Order="1" X="67110" Y="109403" />
				<Coordinate Order="2" X="67110" Y="116257" />
				<Coordinate Order="3" X="52310" Y="116408" />
				<Coordinate Order="4" X="48544" Y="116219" />
				<Coordinate Order="5" X="47339" Y="104884" />
				<Coordinate Order="6" X="47301" Y="103754" />
				<Coordinate Order="7" X="47490" Y="103302" />
				<Coordinate Order="8" X="48054" Y="103377" />
				<Coordinate Order="9" X="48619" Y="103151" />
				<Coordinate Order="10" X="49071" Y="103001" />
				<Coordinate Order="11" X="49862" Y="102699" />
				<Coordinate Order="12" X="50352" Y="102398" />
				<Coordinate Order="13" X="50879" Y="102021" />
				<Coordinate Order="14" X="51670" Y="101720" />
				<Coordinate Order="15" X="52611" Y="101419" />
				<Coordinate Order="16" X="53289" Y="101118" />
				<Coordinate Order="17" X="53816" Y="100892" />
				<Coordinate Order="18" X="54494" Y="100816" />
				<Coordinate Order="19" X="55248" Y="100854" />
				<Coordinate Order="20" X="56415" Y="100816" />
				<Coordinate Order="21" X="57281" Y="100816" />
				<Coordinate Order="22" X="57959" Y="100628" />
				<Coordinate Order="23" X="58562" Y="100666" />
				<Coordinate Order="24" X="59842" Y="100590" />
				<Coordinate Order="25" X="60219" Y="100741" />
				<Coordinate Order="26" X="60671" Y="100854" />
				<Coordinate Order="27" X="61198" Y="100892" />
				<Coordinate Order="28" X="62102" Y="101193" />
				<Coordinate Order="29" X="62554" Y="101268" />
				<Coordinate Order="30" X="63344" Y="101419" />
				<Coordinate Order="31" X="64060" Y="101645" />
				<Coordinate Order="32" X="64625" Y="101833" />
				<Coordinate Order="33" X="64964" Y="102059" />
				<Coordinate Order="34" X="65679" Y="102285" />
				<Coordinate Order="35" X="66244" Y="102699" />
				<Coordinate Order="36" X="66282" Y="102172" />
				<Coordinate Order="37" X="66696" Y="101871" />
				<Coordinate Order="38" X="66922" Y="101909" />
				<Coordinate Order="39" X="67148" Y="101946" />
			</Coordinates>
</Annotation>
<Annotation Name="_2" Type="Polygon" PartOfGroup="_0" Color="#F4FA58">
			<Coordinates>
				<Coordinate Order="0" X="67280" Y="102026" />
				<Coordinate Order="1" X="67243" Y="109505" />
				<Coordinate Order="2" X="68349" Y="109616" />
				<Coordinate Order="3" X="68422" Y="110869" />
				<Coordinate Order="4" X="69712" Y="110905" />
				<Coordinate Order="5" X="69823" Y="112232" />
				<Coordinate Order="6" X="72365" Y="112232" />
				<Coordinate Order="7" X="72512" Y="113485" />
				<Coordinate Order="8" X="73691" Y="113558" />
				<Coordinate Order="9" X="74170" Y="106410" />
				<Coordinate Order="10" X="74281" Y="105821" />
				<Coordinate Order="11" X="74539" Y="105821" />
				<Coordinate Order="12" X="74944" Y="105821" />
				<Coordinate Order="13" X="75313" Y="105894" />
				<Coordinate Order="14" X="75681" Y="105747" />
				<Coordinate Order="15" X="76049" Y="105747" />
				<Coordinate Order="16" X="76528" Y="105673" />
				<Coordinate Order="17" X="76971" Y="105600" />
				<Coordinate Order="18" X="77376" Y="105563" />
				<Coordinate Order="19" X="77671" Y="105526" />
				<Coordinate Order="20" X="78076" Y="105452" />
				<Coordinate Order="21" X="78481" Y="105489" />
				<Coordinate Order="22" X="78850" Y="105489" />
				<Coordinate Order="23" X="79218" Y="105415" />
				<Coordinate Order="24" X="79513" Y="105415" />
				<Coordinate Order="25" X="79881" Y="105452" />
				<Coordinate Order="26" X="80139" Y="105526" />
				<Coordinate Order="27" X="80581" Y="105637" />
				<Coordinate Order="28" X="80876" Y="105673" />
				<Coordinate Order="29" X="81134" Y="105784" />
				<Coordinate Order="30" X="81539" Y="105821" />
				<Coordinate Order="31" X="81797" Y="106042" />
				<Coordinate Order="32" X="82276" Y="105931" />
				<Coordinate Order="33" X="82608" Y="105894" />
				<Coordinate Order="34" X="82903" Y="105931" />
				<Coordinate Order="35" X="82682" Y="105489" />
				<Coordinate Order="36" X="82313" Y="105231" />
				<Coordinate Order="37" X="82018" Y="105158" />
				<Coordinate Order="38" X="81392" Y="104936" />
				<Coordinate Order="39" X="81060" Y="104642" />
				<Coordinate Order="40" X="80913" Y="104347" />
				<Coordinate Order="41" X="80913" Y="103978" />
				<Coordinate Order="42" X="80508" Y="103684" />
				<Coordinate Order="43" X="80029" Y="103573" />
				<Coordinate Order="44" X="79660" Y="103463" />
				<Coordinate Order="45" X="79108" Y="103463" />
				<Coordinate Order="46" X="78518" Y="103463" />
				<Coordinate Order="47" X="77965" Y="103242" />
				<Coordinate Order="48" X="77597" Y="103094" />
				<Coordinate Order="49" X="77118" Y="103057" />
				<Coordinate Order="50" X="76750" Y="102836" />
				<Coordinate Order="51" X="76049" Y="102799" />
				<Coordinate Order="52" X="75570" Y="102763" />
				<Coordinate Order="53" X="75165" Y="102726" />
				<Coordinate Order="54" X="74502" Y="102726" />
				<Coordinate Order="55" X="74133" Y="102652" />
				<Coordinate Order="56" X="73839" Y="102505" />
				<Coordinate Order="57" X="73691" Y="102357" />
			</Coordinates>
</Annotation>
<Annotation Name="_2" Type="Polygon" PartOfGroup="_0" Color="#F4FA58">
			<Coordinates>
				<Coordinate Order="0" X="26714" Y="105553" />
				<Coordinate Order="1" X="25976" Y="106291" />
				<Coordinate Order="2" X="25367" Y="106726" />
				<Coordinate Order="3" X="25498" Y="107030" />
				<Coordinate Order="4" X="25281" Y="107334" />
				<Coordinate Order="5" X="24846" Y="107681" />
				<Coordinate Order="6" X="24238" Y="108290" />
				<Coordinate Order="7" X="23630" Y="109375" />
				<Coordinate Order="8" X="23326" Y="109984" />
				<Coordinate Order="9" X="23196" Y="111200" />
				<Coordinate Order="10" X="23109" Y="112069" />
				<Coordinate Order="11" X="23196" Y="112894" />
				<Coordinate Order="12" X="23543" Y="113545" />
				<Coordinate Order="13" X="23847" Y="114023" />
				<Coordinate Order="14" X="23977" Y="114892" />
				<Coordinate Order="15" X="23934" Y="115674" />
				<Coordinate Order="16" X="23934" Y="116456" />
				<Coordinate Order="17" X="24064" Y="117151" />
				<Coordinate Order="18" X="24064" Y="117672" />
				<Coordinate Order="19" X="24151" Y="118280" />
				<Coordinate Order="20" X="24455" Y="118888" />
				<Coordinate Order="21" X="24716" Y="119366" />
				<Coordinate Order="22" X="25107" Y="120061" />
				<Coordinate Order="23" X="25150" Y="120626" />
				<Coordinate Order="24" X="25628" Y="121060" />
				<Coordinate Order="25" X="26193" Y="121408" />
				<Coordinate Order="26" X="27018" Y="121581" />
				<Coordinate Order="27" X="28147" Y="121408" />
				<Coordinate Order="28" X="29103" Y="121060" />
				<Coordinate Order="29" X="29537" Y="120713" />
				<Coordinate Order="30" X="30363" Y="120539" />
				<Coordinate Order="31" X="31362" Y="120626" />
				<Coordinate Order="32" X="32144" Y="120539" />
				<Coordinate Order="33" X="33143" Y="120800" />
				<Coordinate Order="34" X="34055" Y="120800" />
				<Coordinate Order="35" X="35532" Y="120582" />
				<Coordinate Order="36" X="36357" Y="120191" />
				<Coordinate Order="37" X="37096" Y="119496" />
				<Coordinate Order="38" X="37617" Y="118454" />
				<Coordinate Order="39" X="37791" Y="117672" />
				<Coordinate Order="40" X="38008" Y="116890" />
				<Coordinate Order="41" X="37704" Y="115587" />
				<Coordinate Order="42" X="38138" Y="116325" />
				<Coordinate Order="43" X="38486" Y="117629" />
				<Coordinate Order="44" X="38703" Y="119236" />
				<Coordinate Order="45" X="38746" Y="120148" />
				<Coordinate Order="46" X="39354" Y="120495" />
				<Coordinate Order="47" X="39876" Y="121494" />
				<Coordinate Order="48" X="39876" Y="121755" />
				<Coordinate Order="49" X="40744" Y="122450" />
				<Coordinate Order="50" X="41396" Y="122363" />
				<Coordinate Order="51" X="41352" Y="121755" />
				<Coordinate Order="52" X="41526" Y="121190" />
				<Coordinate Order="53" X="41526" Y="120539" />
				<Coordinate Order="54" X="41613" Y="119931" />
				<Coordinate Order="55" X="42047" Y="119496" />
				<Coordinate Order="56" X="42656" Y="120018" />
				<Coordinate Order="57" X="43481" Y="120104" />
				<Coordinate Order="58" X="44827" Y="119714" />
				<Coordinate Order="59" X="47955" Y="119670" />
				<Coordinate Order="60" X="48476" Y="119714" />
				<Coordinate Order="61" X="48389" Y="116369" />
				<Coordinate Order="62" X="47173" Y="104815" />
				<Coordinate Order="63" X="41352" Y="104554" />
				<Coordinate Order="64" X="41396" Y="106813" />
				<Coordinate Order="65" X="38529" Y="106943" />
				<Coordinate Order="66" X="38659" Y="110809" />
				<Coordinate Order="67" X="34576" Y="110983" />
				<Coordinate Order="68" X="34576" Y="112286" />
				<Coordinate Order="69" X="31883" Y="112199" />
				<Coordinate Order="70" X="31796" Y="105727" />
			</Coordinates>
</Annotation>
<Annotation Name="_2" Type="Polygon" PartOfGroup="_0" Color="#F4FA58">
			<Coordinates>
				<Coordinate Order="0" X="52342" Y="116586" />
				<Coordinate Order="1" X="52299" Y="120278" />
				<Coordinate Order="2" X="54905" Y="120365" />
				<Coordinate Order="3" X="55079" Y="123058" />
				<Coordinate Order="4" X="56338" Y="123102" />
				<Coordinate Order="5" X="56425" Y="131919" />
				<Coordinate Order="6" X="55730" Y="132093" />
				<Coordinate Order="7" X="55252" Y="132354" />
				<Coordinate Order="8" X="55035" Y="131919" />
				<Coordinate Order="9" X="54644" Y="131789" />
				<Coordinate Order="10" X="54253" Y="131572" />
				<Coordinate Order="11" X="53732" Y="131442" />
				<Coordinate Order="12" X="53167" Y="131355" />
				<Coordinate Order="13" X="52907" Y="131833" />
				<Coordinate Order="14" X="52603" Y="132180" />
				<Coordinate Order="15" X="51951" Y="132354" />
				<Coordinate Order="16" X="51691" Y="132180" />
				<Coordinate Order="17" X="51386" Y="131919" />
				<Coordinate Order="18" X="51169" Y="131659" />
				<Coordinate Order="19" X="50909" Y="131442" />
				<Coordinate Order="20" X="50605" Y="131138" />
				<Coordinate Order="21" X="50127" Y="130529" />
				<Coordinate Order="22" X="49779" Y="130095" />
				<Coordinate Order="23" X="49345" Y="130443" />
				<Coordinate Order="24" X="49779" Y="131268" />
				<Coordinate Order="25" X="50214" Y="131833" />
				<Coordinate Order="26" X="50561" Y="132701" />
				<Coordinate Order="27" X="49866" Y="133136" />
				<Coordinate Order="28" X="49432" Y="133787" />
				<Coordinate Order="29" X="49258" Y="134439" />
				<Coordinate Order="30" X="49171" Y="135090" />
				<Coordinate Order="31" X="48824" Y="135264" />
				<Coordinate Order="32" X="48389" Y="135481" />
				<Coordinate Order="33" X="48389" Y="136003" />
				<Coordinate Order="34" X="48389" Y="136394" />
				<Coordinate Order="35" X="47738" Y="136698" />
				<Coordinate Order="36" X="47130" Y="136741" />
				<Coordinate Order="37" X="46131" Y="136567" />
				<Coordinate Order="38" X="45175" Y="136784" />
				<Coordinate Order="39" X="44339" Y="137559" />
				<Coordinate Order="40" X="43497" Y="138371" />
				<Coordinate Order="41" X="42895" Y="138973" />
				<Coordinate Order="42" X="42654" Y="139634" />
				<Coordinate Order="43" X="43045" Y="139965" />
				<Coordinate Order="44" X="43797" Y="139424" />
				<Coordinate Order="45" X="44820" Y="138882" />
				<Coordinate Order="46" X="45302" Y="139003" />
				<Coordinate Order="47" X="45542" Y="139334" />
				<Coordinate Order="48" X="45362" Y="141500" />
				<Coordinate Order="49" X="44941" Y="142643" />
				<Coordinate Order="50" X="46234" Y="142342" />
				<Coordinate Order="51" X="46986" Y="142582" />
				<Coordinate Order="52" X="47166" Y="143485" />
				<Coordinate Order="53" X="45819" Y="146073" />
				<Coordinate Order="54" X="44725" Y="147167" />
				<Coordinate Order="55" X="43152" Y="146962" />
				<Coordinate Order="56" X="42810" Y="145662" />
				<Coordinate Order="57" X="43288" Y="145047" />
				<Coordinate Order="58" X="43979" Y="144603" />
				<Coordinate Order="59" X="44147" Y="144098" />
				<Coordinate Order="60" X="43768" Y="143930" />
				<Coordinate Order="61" X="43305" Y="144435" />
				<Coordinate Order="62" X="42758" Y="144603" />
				<Coordinate Order="63" X="42337" Y="144350" />
				<Coordinate Order="64" X="42211" Y="143509" />
				<Coordinate Order="65" X="42421" Y="143172" />
				<Coordinate Order="66" X="41916" Y="143425" />
				<Coordinate Order="67" X="41327" Y="143593" />
				<Coordinate Order="68" X="41496" Y="141825" />
				<Coordinate Order="69" X="41580" Y="140900" />
				<Coordinate Order="70" X="41411" Y="140268" />
				<Coordinate Order="71" X="41496" Y="139721" />
				<Coordinate Order="72" X="41622" Y="139174" />
				<Coordinate Order="73" X="41622" Y="138501" />
				<Coordinate Order="74" X="41580" Y="137954" />
				<Coordinate Order="75" X="41748" Y="137533" />
				<Coordinate Order="76" X="41748" Y="137154" />
				<Coordinate Order="77" X="42169" Y="136944" />
				<Coordinate Order="78" X="42590" Y="136607" />
				<Coordinate Order="79" X="42674" Y="136228" />
				<Coordinate Order="80" X="42716" Y="135849" />
				<Coordinate Order="81" X="43095" Y="135555" />
				<Coordinate Order="82" X="43473" Y="135344" />
				<Coordinate Order="83" X="43516" Y="135050" />
				<Coordinate Order="84" X="43389" Y="134713" />
				<Coordinate Order="85" X="43347" Y="134376" />
				<Coordinate Order="86" X="43347" Y="134040" />
				<Coordinate Order="87" X="43431" Y="133577" />
				<Coordinate Order="88" X="43558" Y="133282" />
				<Coordinate Order="89" X="43768" Y="132861" />
				<Coordinate Order="90" X="44105" Y="132735" />
				<Coordinate Order="91" X="44526" Y="132651" />
				<Coordinate Order="92" X="44736" Y="132314" />
				<Coordinate Order="93" X="45115" Y="132314" />
				<Coordinate Order="94" X="45325" Y="132062" />
				<Coordinate Order="95" X="45325" Y="131725" />
				<Coordinate Order="96" X="45199" Y="131388" />
				<Coordinate Order="97" X="44989" Y="131262" />
				<Coordinate Order="98" X="44610" Y="130968" />
				<Coordinate Order="99" X="44273" Y="130715" />
				<Coordinate Order="100" X="43852" Y="130378" />
				<Coordinate Order="101" X="43305" Y="130378" />
				<Coordinate Order="102" X="42800" Y="130294" />
				<Coordinate Order="103" X="42379" Y="130589" />
				<Coordinate Order="104" X="42279" Y="130752" />
				<Coordinate Order="105" X="42078" Y="130872" />
				<Coordinate Order="106" X="41877" Y="131013" />
				<Coordinate Order="107" X="41556" Y="131013" />
				<Coordinate Order="108" X="41275" Y="130992" />
				<Coordinate Order="109" X="40793" Y="131053" />
				<Coordinate Order="110" X="40492" Y="131033" />
				<Coordinate Order="111" X="40151" Y="131073" />
				<Coordinate Order="112" X="39930" Y="131153" />
				<Coordinate Order="113" X="39569" Y="131173" />
				<Coordinate Order="114" X="39167" Y="131274" />
				<Coordinate Order="115" X="38826" Y="131434" />
				<Coordinate Order="116" X="38525" Y="131635" />
				<Coordinate Order="117" X="38184" Y="131675" />
				<Coordinate Order="118" X="37902" Y="131595" />
				<Coordinate Order="119" X="37842" Y="131434" />
				<Coordinate Order="120" X="37862" Y="131153" />
				<Coordinate Order="121" X="37923" Y="130832" />
				<Coordinate Order="122" X="37862" Y="130671" />
				<Coordinate Order="123" X="37682" Y="130450" />
				<Coordinate Order="124" X="37762" Y="130290" />
				<Coordinate Order="125" X="37963" Y="130069" />
				<Coordinate Order="126" X="38244" Y="129868" />
				<Coordinate Order="127" X="38465" Y="129668" />
				<Coordinate Order="128" X="39007" Y="129346" />
				<Coordinate Order="129" X="39509" Y="129246" />
				<Coordinate Order="130" X="40191" Y="129025" />
				<Coordinate Order="131" X="40412" Y="128744" />
				<Coordinate Order="132" X="40412" Y="128262" />
				<Coordinate Order="133" X="40452" Y="127861" />
				<Coordinate Order="134" X="40291" Y="127780" />
				<Coordinate Order="135" X="40171" Y="127459" />
				<Coordinate Order="136" X="40171" Y="127058" />
				<Coordinate Order="137" X="40171" Y="126777" />
				<Coordinate Order="138" X="40071" Y="126516" />
				<Coordinate Order="139" X="39729" Y="126375" />
				<Coordinate Order="140" X="39569" Y="126174" />
				<Coordinate Order="141" X="39468" Y="125954" />
				<Coordinate Order="142" X="39288" Y="125612" />
				<Coordinate Order="143" X="39248" Y="125311" />
				<Coordinate Order="144" X="39348" Y="124970" />
				<Coordinate Order="145" X="39348" Y="124629" />
				<Coordinate Order="146" X="39107" Y="124207" />
				<Coordinate Order="147" X="39180" Y="123826" />
				<Coordinate Order="148" X="40142" Y="124389" />
				<Coordinate Order="149" X="41150" Y="125187" />
				<Coordinate Order="150" X="41573" Y="125539" />
				<Coordinate Order="151" X="41878" Y="126243" />
				<Coordinate Order="152" X="42042" Y="126806" />
				<Coordinate Order="153" X="42417" Y="127064" />
				<Coordinate Order="154" X="42769" Y="127674" />
				<Coordinate Order="155" X="43332" Y="128049" />
				<Coordinate Order="156" X="44083" Y="128214" />
				<Coordinate Order="157" X="44951" Y="128237" />
				<Coordinate Order="158" X="45279" Y="127721" />
				<Coordinate Order="159" X="45608" Y="127041" />
				<Coordinate Order="160" X="45960" Y="126595" />
				<Coordinate Order="161" X="46101" Y="126079" />
				<Coordinate Order="162" X="45655" Y="124953" />
				<Coordinate Order="163" X="45256" Y="123873" />
				<Coordinate Order="164" X="44904" Y="122794" />
				<Coordinate Order="165" X="44646" Y="121903" />
				<Coordinate Order="166" X="44669" Y="120448" />
				<Coordinate Order="167" X="44716" Y="119815" />
				<Coordinate Order="168" X="48470" Y="119838" />
				<Coordinate Order="169" X="48570" Y="116381" />
			</Coordinates>
</Annotation>
</Annotations>
	<AnnotationGroups>
		<Group Name="_0" PartOfGroup="_0" Color="#0000ff">
			<Attributes />
		</Group>
	</AnnotationGroups>
</ASAP_Annotations>
