<?xml version="1.0"?>
<ASAP_Annotations>
<Annotations>
<Annotation Name="_0" Type="Polygon" PartOfGroup="_0" Color="#F4FA58">
			<Coordinates>
				<Coordinate Order="0" X="49644" Y="9023" />
				<Coordinate Order="1" X="49320" Y="8406" />
				<Coordinate Order="2" X="50496" Y="8700" />
				<Coordinate Order="3" X="50643" Y="9347" />
				<Coordinate Order="4" X="51789" Y="9670" />
				<Coordinate Order="5" X="52995" Y="9729" />
				<Coordinate Order="6" X="54170" Y="9553" />
				<Coordinate Order="7" X="55346" Y="9435" />
				<Coordinate Order="8" X="56463" Y="8994" />
				<Coordinate Order="9" X="57521" Y="8465" />
				<Coordinate Order="10" X="58285" Y="7554" />
				<Coordinate Order="11" X="58344" Y="6378" />
				<Coordinate Order="12" X="58638" Y="5232" />
				<Coordinate Order="13" X="59814" Y="5085" />
				<Coordinate Order="14" X="60960" Y="5438" />
				<Coordinate Order="15" X="62136" Y="5614" />
				<Coordinate Order="16" X="63311" Y="5673" />
				<Coordinate Order="17" X="63958" Y="6672" />
				<Coordinate Order="18" X="65016" Y="7201" />
				<Coordinate Order="19" X="66221" Y="7436" />
				<Coordinate Order="20" X="67367" Y="7701" />
				<Coordinate Order="21" X="68426" Y="8259" />
				<Coordinate Order="22" X="69307" Y="9082" />
				<Coordinate Order="23" X="69836" Y="10140" />
				<Coordinate Order="24" X="70483" Y="11169" />
				<Coordinate Order="25" X="71688" Y="11434" />
				<Coordinate Order="26" X="72864" Y="11345" />
				<Coordinate Order="27" X="74098" Y="11345" />
				<Coordinate Order="28" X="75333" Y="11257" />
				<Coordinate Order="29" X="76508" Y="11052" />
				<Coordinate Order="30" X="77655" Y="10728" />
				<Coordinate Order="31" X="78147" Y="10713" />
				<Coordinate Order="32" X="78526" Y="10785" />
				<Coordinate Order="33" X="78886" Y="10867" />
				<Coordinate Order="34" X="79210" Y="11074" />
				<Coordinate Order="35" X="79400" Y="11389" />
				<Coordinate Order="36" X="79607" Y="11695" />
				<Coordinate Order="37" X="79850" Y="12002" />
				<Coordinate Order="38" X="80111" Y="12263" />
				<Coordinate Order="39" X="80391" Y="12497" />
				<Coordinate Order="40" X="80688" Y="12732" />
				<Coordinate Order="41" X="80985" Y="12948" />
				<Coordinate Order="42" X="81319" Y="13119" />
				<Coordinate Order="43" X="81634" Y="13326" />
				<Coordinate Order="44" X="81886" Y="13597" />
				<Coordinate Order="45" X="81886" Y="13975" />
				<Coordinate Order="46" X="81742" Y="14336" />
				<Coordinate Order="47" X="81706" Y="14705" />
				<Coordinate Order="48" X="81886" Y="15038" />
				<Coordinate Order="49" X="82166" Y="15273" />
				<Coordinate Order="50" X="82463" Y="15507" />
				<Coordinate Order="51" X="82715" Y="15786" />
				<Coordinate Order="52" X="82986" Y="16029" />
				<Coordinate Order="53" X="83265" Y="16264" />
				<Coordinate Order="54" X="83110" Y="15510" />
				<Coordinate Order="55" X="82910" Y="15339" />
				<Coordinate Order="56" X="82754" Y="15085" />
				<Coordinate Order="57" X="82559" Y="14734" />
				<Coordinate Order="58" X="82676" Y="14421" />
				<Coordinate Order="59" X="83047" Y="14265" />
				<Coordinate Order="60" X="83242" Y="14089" />
				<Coordinate Order="61" X="83262" Y="13796" />
				<Coordinate Order="62" X="83379" Y="13502" />
				<Coordinate Order="63" X="83496" Y="13366" />
				<Coordinate Order="64" X="84044" Y="13327" />
				<Coordinate Order="65" X="84259" Y="13151" />
				<Coordinate Order="66" X="84571" Y="12799" />
				<Coordinate Order="67" X="84825" Y="12682" />
				<Coordinate Order="68" X="85197" Y="12682" />
				<Coordinate Order="69" X="85626" Y="12955" />
				<Coordinate Order="70" X="85900" Y="13248" />
				<Coordinate Order="71" X="86115" Y="13932" />
				<Coordinate Order="72" X="85978" Y="14714" />
				<Coordinate Order="73" X="85920" Y="15261" />
				<Coordinate Order="74" X="86174" Y="16590" />
				<Coordinate Order="75" X="86271" Y="17059" />
				<Coordinate Order="76" X="86428" Y="17469" />
				<Coordinate Order="77" X="86643" Y="18036" />
				<Coordinate Order="78" X="87092" Y="18700" />
				<Coordinate Order="79" X="87307" Y="19072" />
				<Coordinate Order="80" X="87522" Y="19404" />
				<Coordinate Order="81" X="87854" Y="19970" />
				<Coordinate Order="82" X="88206" Y="20947" />
				<Coordinate Order="83" X="88186" Y="21123" />
				<Coordinate Order="84" X="88284" Y="21885" />
				<Coordinate Order="85" X="88343" Y="22413" />
				<Coordinate Order="86" X="88343" Y="23253" />
				<Coordinate Order="87" X="88303" Y="24015" />
				<Coordinate Order="88" X="88303" Y="24562" />
				<Coordinate Order="89" X="88421" Y="25324" />
				<Coordinate Order="90" X="88675" Y="25950" />
				<Coordinate Order="91" X="88792" Y="26536" />
				<Coordinate Order="92" X="88733" Y="27239" />
				<Coordinate Order="93" X="88636" Y="27708" />
				<Coordinate Order="94" X="88675" Y="28588" />
				<Coordinate Order="95" X="88577" Y="29350" />
				<Coordinate Order="96" X="88460" Y="29506" />
				<Coordinate Order="97" X="88264" Y="30073" />
				<Coordinate Order="98" X="88499" Y="30405" />
				<Coordinate Order="99" X="88577" Y="30854" />
				<Coordinate Order="100" X="88499" Y="31148" />
				<Coordinate Order="101" X="88089" Y="31226" />
				<Coordinate Order="102" X="88128" Y="31675" />
				<Coordinate Order="103" X="88225" Y="32105" />
				<Coordinate Order="104" X="88128" Y="32457" />
				<Coordinate Order="105" X="88206" Y="32906" />
				<Coordinate Order="106" X="88284" Y="33258" />
				<Coordinate Order="107" X="88284" Y="33571" />
				<Coordinate Order="108" X="87795" Y="34020" />
				<Coordinate Order="109" X="87717" Y="34430" />
				<Coordinate Order="110" X="87444" Y="35310" />
				<Coordinate Order="111" X="87620" Y="35525" />
				<Coordinate Order="112" X="87913" Y="36384" />
				<Coordinate Order="113" X="87834" Y="36834" />
				<Coordinate Order="114" X="87209" Y="37166" />
				<Coordinate Order="115" X="87131" Y="37381" />
				<Coordinate Order="116" X="86877" Y="37635" />
				<Coordinate Order="117" X="86193" Y="36697" />
				<Coordinate Order="118" X="86232" Y="35818" />
				<Coordinate Order="119" X="86252" Y="35017" />
				<Coordinate Order="120" X="86447" Y="34372" />
				<Coordinate Order="121" X="86623" Y="33629" />
				<Coordinate Order="122" X="86682" Y="32808" />
				<Coordinate Order="123" X="86388" Y="32281" />
				<Coordinate Order="124" X="86174" Y="32242" />
				<Coordinate Order="125" X="85939" Y="33102" />
				<Coordinate Order="126" X="85939" Y="33727" />
				<Coordinate Order="127" X="85802" Y="34841" />
				<Coordinate Order="128" X="85666" Y="35212" />
				<Coordinate Order="129" X="85451" Y="35427" />
				<Coordinate Order="130" X="84962" Y="35798" />
				<Coordinate Order="131" X="84552" Y="35857" />
				<Coordinate Order="132" X="84474" Y="35994" />
				<Coordinate Order="133" X="84298" Y="36267" />
				<Coordinate Order="134" X="84434" Y="36756" />
				<Coordinate Order="135" X="84454" Y="36990" />
				<Coordinate Order="136" X="83321" Y="37166" />
				<Coordinate Order="137" X="83379" Y="37635" />
				<Coordinate Order="138" X="83418" Y="38280" />
				<Coordinate Order="139" X="83184" Y="38573" />
				<Coordinate Order="140" X="82617" Y="38788" />
				<Coordinate Order="141" X="82285" Y="39081" />
				<Coordinate Order="142" X="81953" Y="39335" />
				<Coordinate Order="143" X="81836" Y="40117" />
				<Coordinate Order="144" X="81679" Y="40781" />
				<Coordinate Order="145" X="81132" Y="41387" />
				<Coordinate Order="146" X="80898" Y="41680" />
				<Coordinate Order="147" X="80272" Y="42188" />
				<Coordinate Order="148" X="79100" Y="42540" />
				<Coordinate Order="149" X="78631" Y="42970" />
				<Coordinate Order="150" X="77927" Y="43712" />
				<Coordinate Order="151" X="77517" Y="44630" />
				<Coordinate Order="152" X="76716" Y="45236" />
				<Coordinate Order="153" X="76208" Y="45959" />
				<Coordinate Order="154" X="75915" Y="46526" />
				<Coordinate Order="155" X="74821" Y="47444" />
				<Coordinate Order="156" X="74098" Y="48050" />
				<Coordinate Order="157" X="73472" Y="48949" />
				<Coordinate Order="158" X="72710" Y="49926" />
				<Coordinate Order="159" X="72065" Y="50629" />
				<Coordinate Order="160" X="71479" Y="51274" />
				<Coordinate Order="161" X="70717" Y="51724" />
				<Coordinate Order="162" X="69955" Y="52427" />
				<Coordinate Order="163" X="69271" Y="52896" />
				<Coordinate Order="164" X="69017" Y="53092" />
				<Coordinate Order="165" X="68020" Y="53775" />
				<Coordinate Order="166" X="67395" Y="53990" />
				<Coordinate Order="167" X="67200" Y="54244" />
				<Coordinate Order="168" X="66907" Y="54401" />
				<Coordinate Order="169" X="66457" Y="54342" />
				<Coordinate Order="170" X="66008" Y="55006" />
				<Coordinate Order="171" X="65695" Y="55554" />
				<Coordinate Order="172" X="65207" Y="55827" />
				<Coordinate Order="173" X="64738" Y="55808" />
				<Coordinate Order="174" X="64132" Y="55690" />
				<Coordinate Order="175" X="63897" Y="56335" />
				<Coordinate Order="176" X="63800" Y="56921" />
				<Coordinate Order="177" X="64034" Y="57234" />
				<Coordinate Order="178" X="64366" Y="58172" />
				<Coordinate Order="179" X="64230" Y="59130" />
				<Coordinate Order="180" X="64171" Y="59501" />
				<Coordinate Order="181" X="64112" Y="60400" />
				<Coordinate Order="182" X="64190" Y="61180" />
				<Coordinate Order="183" X="64361" Y="61949" />
				<Coordinate Order="184" X="64425" Y="62760" />
				<Coordinate Order="185" X="64596" Y="63827" />
				<Coordinate Order="186" X="64596" Y="64617" />
				<Coordinate Order="187" X="64190" Y="65514" />
				<Coordinate Order="188" X="63614" Y="65855" />
				<Coordinate Order="189" X="63165" Y="66026" />
				<Coordinate Order="190" X="62760" Y="66197" />
				<Coordinate Order="191" X="62610" Y="66645" />
				<Coordinate Order="192" X="62717" Y="67029" />
				<Coordinate Order="193" X="62418" Y="67563" />
				<Coordinate Order="194" X="62141" Y="68097" />
				<Coordinate Order="195" X="61500" Y="68801" />
				<Coordinate Order="196" X="60796" Y="68673" />
				<Coordinate Order="197" X="60561" Y="68780" />
				<Coordinate Order="198" X="60390" Y="68694" />
				<Coordinate Order="199" X="60732" Y="69185" />
				<Coordinate Order="200" X="61095" Y="69313" />
				<Coordinate Order="201" X="61223" Y="69484" />
				<Coordinate Order="202" X="61458" Y="70082" />
				<Coordinate Order="203" X="61458" Y="70530" />
				<Coordinate Order="204" X="61202" Y="71064" />
				<Coordinate Order="205" X="60903" Y="70978" />
				<Coordinate Order="206" X="60326" Y="70637" />
				<Coordinate Order="207" X="60177" Y="70082" />
				<Coordinate Order="208" X="59451" Y="69826" />
				<Coordinate Order="209" X="59665" Y="70829" />
				<Coordinate Order="210" X="59814" Y="71320" />
				<Coordinate Order="211" X="59665" Y="71491" />
				<Coordinate Order="212" X="58811" Y="71491" />
				<Coordinate Order="213" X="57786" Y="71512" />
				<Coordinate Order="214" X="57039" Y="71597" />
				<Coordinate Order="215" X="56420" Y="71576" />
				<Coordinate Order="216" X="55630" Y="71341" />
				<Coordinate Order="217" X="55694" Y="71128" />
				<Coordinate Order="218" X="55395" Y="70893" />
				<Coordinate Order="219" X="55224" Y="70381" />
				<Coordinate Order="220" X="55395" Y="69505" />
				<Coordinate Order="221" X="54947" Y="69207" />
				<Coordinate Order="222" X="54392" Y="68737" />
				<Coordinate Order="223" X="53986" Y="69014" />
				<Coordinate Order="224" X="53581" Y="68182" />
				<Coordinate Order="225" X="53389" Y="68758" />
				<Coordinate Order="226" X="53111" Y="68502" />
				<Coordinate Order="227" X="52641" Y="67648" />
				<Coordinate Order="228" X="52343" Y="67328" />
				<Coordinate Order="229" X="52150" Y="66922" />
				<Coordinate Order="230" X="52769" Y="66922" />
				<Coordinate Order="231" X="52471" Y="66730" />
				<Coordinate Order="232" X="51916" Y="66346" />
				<Coordinate Order="233" X="51489" Y="65770" />
				<Coordinate Order="234" X="51574" Y="65343" />
				<Coordinate Order="235" X="51702" Y="64724" />
				<Coordinate Order="236" X="52001" Y="64382" />
				<Coordinate Order="237" X="52214" Y="63870" />
				<Coordinate Order="238" X="52641" Y="63037" />
				<Coordinate Order="239" X="52898" Y="62418" />
				<Coordinate Order="240" X="53944" Y="61778" />
				<Coordinate Order="241" X="54776" Y="61522" />
				<Coordinate Order="242" X="55118" Y="61351" />
				<Coordinate Order="243" X="56249" Y="61009" />
				<Coordinate Order="244" X="57167" Y="60817" />
				<Coordinate Order="245" X="58021" Y="60817" />
				<Coordinate Order="246" X="58533" Y="60689" />
				<Coordinate Order="247" X="58811" Y="60412" />
				<Coordinate Order="248" X="57999" Y="60027" />
				<Coordinate Order="249" X="57167" Y="59750" />
				<Coordinate Order="250" X="56655" Y="59238" />
				<Coordinate Order="251" X="56847" Y="58704" />
				<Coordinate Order="252" X="57168" Y="58406" />
				<Coordinate Order="253" X="57032" Y="57997" />
				<Coordinate Order="254" X="57134" Y="57509" />
				<Coordinate Order="255" X="57463" Y="57089" />
				<Coordinate Order="256" X="57509" Y="56771" />
				<Coordinate Order="257" X="57259" Y="56419" />
				<Coordinate Order="258" X="57089" Y="56112" />
				<Coordinate Order="259" X="57191" Y="55669" />
				<Coordinate Order="260" X="57373" Y="55374" />
				<Coordinate Order="261" X="57429" Y="55159" />
				<Coordinate Order="262" X="57463" Y="54807" />
				<Coordinate Order="263" X="57498" Y="54159" />
				<Coordinate Order="264" X="57702" Y="53569" />
				<Coordinate Order="265" X="57793" Y="53024" />
				<Coordinate Order="266" X="57895" Y="52558" />
				<Coordinate Order="267" X="58201" Y="52002" />
				<Coordinate Order="268" X="58883" Y="51298" />
				<Coordinate Order="269" X="59326" Y="50855" />
				<Coordinate Order="270" X="59139" Y="50737" />
				<Coordinate Order="271" X="59152" Y="50552" />
				<Coordinate Order="272" X="59447" Y="49973" />
				<Coordinate Order="273" X="59521" Y="49541" />
				<Coordinate Order="274" X="59497" Y="48827" />
				<Coordinate Order="275" X="59546" Y="48322" />
				<Coordinate Order="276" X="59669" Y="47681" />
				<Coordinate Order="277" X="59669" Y="46905" />
				<Coordinate Order="278" X="59497" Y="46424" />
				<Coordinate Order="279" X="59509" Y="45956" />
				<Coordinate Order="280" X="59792" Y="45550" />
				<Coordinate Order="281" X="60248" Y="45303" />
				<Coordinate Order="282" X="60433" Y="45217" />
				<Coordinate Order="283" X="60495" Y="44934" />
				<Coordinate Order="284" X="60482" Y="44391" />
				<Coordinate Order="285" X="60753" Y="43357" />
				<Coordinate Order="286" X="61308" Y="42667" />
				<Coordinate Order="287" X="61813" Y="41915" />
				<Coordinate Order="288" X="62306" Y="41336" />
				<Coordinate Order="289" X="62503" Y="41090" />
				<Coordinate Order="290" X="62823" Y="40658" />
				<Coordinate Order="291" X="63168" Y="40190" />
				<Coordinate Order="292" X="63513" Y="39660" />
				<Coordinate Order="293" X="63698" Y="39217" />
				<Coordinate Order="294" X="63870" Y="38675" />
				<Coordinate Order="295" X="64277" Y="38231" />
				<Coordinate Order="296" X="64733" Y="37985" />
				<Coordinate Order="297" X="65189" Y="37812" />
				<Coordinate Order="298" X="65509" Y="37997" />
				<Coordinate Order="299" X="65546" Y="38354" />
				<Coordinate Order="300" X="65657" Y="38958" />
				<Coordinate Order="301" X="65694" Y="39143" />
				<Coordinate Order="302" X="66199" Y="39020" />
				<Coordinate Order="303" X="66470" Y="39377" />
				<Coordinate Order="304" X="66261" Y="40079" />
				<Coordinate Order="305" X="66002" Y="40424" />
				<Coordinate Order="306" X="66076" Y="40547" />
				<Coordinate Order="307" X="66544" Y="40461" />
				<Coordinate Order="308" X="66741" Y="39426" />
				<Coordinate Order="309" X="66877" Y="38970" />
				<Coordinate Order="310" X="67333" Y="38588" />
				<Coordinate Order="311" X="67690" Y="38625" />
				<Coordinate Order="312" X="68023" Y="38970" />
				<Coordinate Order="313" X="68380" Y="38736" />
				<Coordinate Order="314" X="68589" Y="39131" />
				<Coordinate Order="315" X="68589" Y="39784" />
				<Coordinate Order="316" X="68491" Y="40128" />
				<Coordinate Order="317" X="68096" Y="40449" />
				<Coordinate Order="318" X="68700" Y="40646" />
				<Coordinate Order="319" X="69094" Y="40498" />
				<Coordinate Order="320" X="69218" Y="40005" />
				<Coordinate Order="321" X="69341" Y="39340" />
				<Coordinate Order="322" X="69563" Y="39020" />
				<Coordinate Order="323" X="69871" Y="38514" />
				<Coordinate Order="324" X="70635" Y="38330" />
				<Coordinate Order="325" X="70967" Y="38391" />
				<Coordinate Order="326" X="71324" Y="38022" />
				<Coordinate Order="327" X="71657" Y="37751" />
				<Coordinate Order="328" X="71891" Y="37319" />
				<Coordinate Order="329" X="71386" Y="37344" />
				<Coordinate Order="330" X="71004" Y="37553" />
				<Coordinate Order="331" X="70524" Y="37714" />
				<Coordinate Order="332" X="70326" Y="37664" />
				<Coordinate Order="333" X="70376" Y="37221" />
				<Coordinate Order="334" X="70573" Y="36580" />
				<Coordinate Order="335" X="70893" Y="35767" />
				<Coordinate Order="336" X="71361" Y="35200" />
				<Coordinate Order="337" X="72027" Y="34658" />
				<Coordinate Order="338" X="72889" Y="34215" />
				<Coordinate Order="339" X="73407" Y="34104" />
				<Coordinate Order="340" X="73973" Y="34017" />
				<Coordinate Order="341" X="74417" Y="34165" />
				<Coordinate Order="342" X="74861" Y="34387" />
				<Coordinate Order="343" X="75070" Y="34560" />
				<Coordinate Order="344" X="75452" Y="34461" />
				<Coordinate Order="345" X="75550" Y="34116" />
				<Coordinate Order="346" X="75846" Y="33783" />
				<Coordinate Order="347" X="76290" Y="33599" />
				<Coordinate Order="348" X="76351" Y="33352" />
				<Coordinate Order="349" X="76056" Y="33377" />
				<Coordinate Order="350" X="75760" Y="33549" />
				<Coordinate Order="351" X="75058" Y="33475" />
				<Coordinate Order="352" X="74540" Y="33574" />
				<Coordinate Order="353" X="74368" Y="33820" />
				<Coordinate Order="354" X="73591" Y="33820" />
				<Coordinate Order="355" X="73074" Y="33833" />
				<Coordinate Order="356" X="72322" Y="33907" />
				<Coordinate Order="357" X="71706" Y="33944" />
				<Coordinate Order="358" X="71559" Y="33820" />
				<Coordinate Order="359" X="71423" Y="33697" />
				<Coordinate Order="360" X="71337" Y="33549" />
				<Coordinate Order="361" X="71004" Y="33180" />
				<Coordinate Order="362" X="70548" Y="32946" />
				<Coordinate Order="363" X="70068" Y="32736" />
				<Coordinate Order="364" X="69772" Y="32293" />
				<Coordinate Order="365" X="69612" Y="31824" />
				<Coordinate Order="366" X="69563" Y="31332" />
				<Coordinate Order="367" X="69563" Y="30814" />
				<Coordinate Order="368" X="69575" Y="30309" />
				<Coordinate Order="369" X="69575" Y="29791" />
				<Coordinate Order="370" X="69513" Y="29286" />
				<Coordinate Order="371" X="69587" Y="28793" />
				<Coordinate Order="372" X="69538" Y="28301" />
				<Coordinate Order="373" X="69513" Y="27795" />
				<Coordinate Order="374" X="69550" Y="27303" />
				<Coordinate Order="375" X="69452" Y="26798" />
				<Coordinate Order="376" X="69637" Y="25836" />
				<Coordinate Order="377" X="69883" Y="25097" />
				<Coordinate Order="378" X="70117" Y="24752" />
				<Coordinate Order="379" X="70610" Y="24863" />
				<Coordinate Order="380" X="71374" Y="25097" />
				<Coordinate Order="381" X="71953" Y="25294" />
				<Coordinate Order="382" X="72470" Y="25245" />
				<Coordinate Order="383" X="73308" Y="24949" />
				<Coordinate Order="384" X="73715" Y="24666" />
				<Coordinate Order="385" X="73628" Y="24358" />
				<Coordinate Order="386" X="72655" Y="24149" />
				<Coordinate Order="387" X="71867" Y="24395" />
				<Coordinate Order="388" X="71361" Y="24432" />
				<Coordinate Order="389" X="71078" Y="24407" />
				<Coordinate Order="390" X="70622" Y="24395" />
				<Coordinate Order="391" X="70006" Y="24210" />
				<Coordinate Order="392" X="69821" Y="23471" />
				<Coordinate Order="393" X="68552" Y="22756" />
				<Coordinate Order="394" X="68355" Y="21906" />
				<Coordinate Order="395" X="68035" Y="21315" />
				<Coordinate Order="396" X="67764" Y="20859" />
				<Coordinate Order="397" X="67653" Y="20637" />
				<Coordinate Order="398" X="67542" Y="20489" />
				<Coordinate Order="399" X="67259" Y="20366" />
				<Coordinate Order="400" X="67000" Y="20465" />
				<Coordinate Order="401" X="67135" Y="20994" />
				<Coordinate Order="402" X="67554" Y="21413" />
				<Coordinate Order="403" X="67838" Y="22103" />
				<Coordinate Order="404" X="68059" Y="22806" />
				<Coordinate Order="405" X="68269" Y="23360" />
				<Coordinate Order="406" X="68441" Y="23927" />
				<Coordinate Order="407" X="68552" Y="24407" />
				<Coordinate Order="408" X="68528" Y="24826" />
				<Coordinate Order="409" X="68466" Y="25331" />
				<Coordinate Order="410" X="68466" Y="26021" />
				<Coordinate Order="411" X="68306" Y="26539" />
				<Coordinate Order="412" X="67456" Y="26995" />
				<Coordinate Order="413" X="67320" Y="27167" />
				<Coordinate Order="414" X="67283" Y="27709" />
				<Coordinate Order="415" X="67271" Y="27968" />
				<Coordinate Order="416" X="67394" Y="28177" />
				<Coordinate Order="417" X="67431" Y="28806" />
				<Coordinate Order="418" X="67185" Y="29471" />
				<Coordinate Order="419" X="67419" Y="29730" />
				<Coordinate Order="420" X="67702" Y="30149" />
				<Coordinate Order="421" X="67776" Y="30543" />
				<Coordinate Order="422" X="67394" Y="31171" />
				<Coordinate Order="423" X="66877" Y="31319" />
				<Coordinate Order="424" X="65842" Y="31171" />
				<Coordinate Order="425" X="65731" Y="31430" />
				<Coordinate Order="426" X="66113" Y="32083" />
				<Coordinate Order="427" X="66285" Y="32773" />
				<Coordinate Order="428" X="65854" Y="33648" />
				<Coordinate Order="429" X="65719" Y="33931" />
				<Coordinate Order="430" X="64881" Y="34350" />
				<Coordinate Order="431" X="64560" Y="34584" />
				<Coordinate Order="432" X="64474" Y="34966" />
				<Coordinate Order="433" X="64634" Y="35176" />
				<Coordinate Order="434" X="64450" Y="35594" />
				<Coordinate Order="435" X="63895" Y="36075" />
				<Coordinate Order="436" X="63168" Y="36408" />
				<Coordinate Order="437" X="62934" Y="36851" />
				<Coordinate Order="438" X="62564" Y="37208" />
				<Coordinate Order="439" X="62146" Y="37689" />
				<Coordinate Order="440" X="61776" Y="38009" />
				<Coordinate Order="441" X="60593" Y="38983" />
				<Coordinate Order="442" X="60408" Y="39315" />
				<Coordinate Order="443" X="59866" Y="39784" />
				<Coordinate Order="444" X="59632" Y="39931" />
				<Coordinate Order="445" X="59496" Y="39933" />
				<Coordinate Order="446" X="59344" Y="40017" />
				<Coordinate Order="447" X="59286" Y="40121" />
				<Coordinate Order="448" X="59237" Y="40207" />
				<Coordinate Order="449" X="59168" Y="40377" />
				<Coordinate Order="450" X="59116" Y="40524" />
				<Coordinate Order="451" X="59096" Y="40645" />
				<Coordinate Order="452" X="59076" Y="40731" />
				<Coordinate Order="453" X="59050" Y="40792" />
				<Coordinate Order="454" X="58802" Y="41224" />
				<Coordinate Order="455" X="58661" Y="41417" />
				<Coordinate Order="456" X="58629" Y="41532" />
				<Coordinate Order="457" X="58531" Y="41812" />
				<Coordinate Order="458" X="58488" Y="41936" />
				<Coordinate Order="459" X="58433" Y="42040" />
				<Coordinate Order="460" X="58422" Y="42074" />
				<Coordinate Order="461" X="58141" Y="42619" />
				<Coordinate Order="462" X="57904" Y="42951" />
				<Coordinate Order="463" X="57537" Y="43567" />
				<Coordinate Order="464" X="56849" Y="44184" />
				<Coordinate Order="465" X="56303" Y="44694" />
				<Coordinate Order="466" X="56007" Y="45038" />
				<Coordinate Order="467" X="55473" Y="45512" />
				<Coordinate Order="468" X="54525" Y="45987" />
				<Coordinate Order="469" X="53884" Y="46402" />
				<Coordinate Order="470" X="53256" Y="46923" />
				<Coordinate Order="471" X="52853" Y="47338" />
				<Coordinate Order="472" X="52473" Y="47635" />
				<Coordinate Order="473" X="51584" Y="48109" />
				<Coordinate Order="474" X="51892" Y="47623" />
				<Coordinate Order="475" X="52319" Y="47410" />
				<Coordinate Order="476" X="53030" Y="46627" />
				<Coordinate Order="477" X="53517" Y="46022" />
				<Coordinate Order="478" X="53920" Y="45643" />
				<Coordinate Order="479" X="54809" Y="44919" />
				<Coordinate Order="480" X="55165" Y="44338" />
				<Coordinate Order="481" X="55829" Y="43734" />
				<Coordinate Order="482" X="56208" Y="43461" />
				<Coordinate Order="483" X="56718" Y="43058" />
				<Coordinate Order="484" X="57074" Y="42690" />
				<Coordinate Order="485" X="57382" Y="42429" />
				<Coordinate Order="486" X="57857" Y="41884" />
				<Coordinate Order="487" X="57940" Y="41646" />
				<Coordinate Order="488" X="58141" Y="41291" />
				<Coordinate Order="489" X="58473" Y="40745" />
				<Coordinate Order="490" X="58639" Y="40389" />
				<Coordinate Order="491" X="58734" Y="40034" />
				<Coordinate Order="492" X="58770" Y="39761" />
				<Coordinate Order="493" X="58841" Y="39488" />
				<Coordinate Order="494" X="59078" Y="39109" />
				<Coordinate Order="495" X="59315" Y="38824" />
				<Coordinate Order="496" X="59600" Y="38492" />
				<Coordinate Order="497" X="59861" Y="38208" />
				<Coordinate Order="498" X="60311" Y="37733" />
				<Coordinate Order="499" X="60466" Y="37543" />
				<Coordinate Order="500" X="60916" Y="36974" />
				<Coordinate Order="501" X="61177" Y="36500" />
				<Coordinate Order="502" X="61414" Y="36097" />
				<Coordinate Order="503" X="61568" Y="35717" />
				<Coordinate Order="504" X="61675" Y="35314" />
				<Coordinate Order="505" X="61723" Y="34982" />
				<Coordinate Order="506" X="61734" Y="34508" />
				<Coordinate Order="507" X="61794" Y="34033" />
				<Coordinate Order="508" X="61900" Y="33559" />
				<Coordinate Order="509" X="62102" Y="33108" />
				<Coordinate Order="510" X="62256" Y="32610" />
				<Coordinate Order="511" X="62280" Y="32124" />
				<Coordinate Order="512" X="62327" Y="31650" />
				<Coordinate Order="513" X="62387" Y="31176" />
				<Coordinate Order="514" X="62351" Y="30701" />
				<Coordinate Order="515" X="62292" Y="30227" />
				<Coordinate Order="516" X="62114" Y="29776" />
				<Coordinate Order="517" X="61924" Y="29314" />
				<Coordinate Order="518" X="61900" Y="28816" />
				<Coordinate Order="519" X="62066" Y="28365" />
				<Coordinate Order="520" X="62221" Y="27914" />
				<Coordinate Order="521" X="62173" Y="27428" />
				<Coordinate Order="522" X="62161" Y="27310" />
				<Coordinate Order="523" X="62185" Y="26835" />
				<Coordinate Order="524" X="62244" Y="26361" />
				<Coordinate Order="525" X="62292" Y="25887" />
				<Coordinate Order="526" X="62149" Y="25412" />
				<Coordinate Order="527" X="61995" Y="24950" />
				<Coordinate Order="528" X="61924" Y="24464" />
				<Coordinate Order="529" X="61758" Y="24001" />
				<Coordinate Order="530" X="61592" Y="23551" />
				<Coordinate Order="531" X="61616" Y="23053" />
				<Coordinate Order="532" X="61758" Y="22578" />
				<Coordinate Order="533" X="61723" Y="21831" />
				<Coordinate Order="534" X="61723" Y="21345" />
				<Coordinate Order="535" X="61616" Y="20883" />
				<Coordinate Order="536" X="61438" Y="20420" />
				<Coordinate Order="537" X="61260" Y="19946" />
				<Coordinate Order="538" X="61118" Y="19483" />
				<Coordinate Order="539" X="61023" Y="19009" />
				<Coordinate Order="540" X="60893" Y="18546" />
				<Coordinate Order="541" X="60809" Y="18060" />
				<Coordinate Order="542" X="60786" Y="17586" />
				<Coordinate Order="543" X="60845" Y="17112" />
				<Coordinate Order="544" X="60786" Y="16614" />
				<Coordinate Order="545" X="60667" Y="16151" />
				<Coordinate Order="546" X="60311" Y="15819" />
				<Coordinate Order="547" X="59920" Y="15546" />
				<Coordinate Order="548" X="59529" Y="15274" />
				<Coordinate Order="549" X="59173" Y="14941" />
				<Coordinate Order="550" X="58960" Y="14526" />
				<Coordinate Order="551" X="58639" Y="14159" />
				<Coordinate Order="552" X="58236" Y="13898" />
				<Coordinate Order="553" X="57916" Y="13518" />
				<Coordinate Order="554" X="57975" Y="13032" />
				<Coordinate Order="555" X="58141" Y="12570" />
				<Coordinate Order="556" X="58165" Y="12095" />
				<Coordinate Order="557" X="58165" Y="11609" />
				<Coordinate Order="558" X="58236" Y="11135" />
				<Coordinate Order="559" X="58307" Y="10637" />
				<Coordinate Order="560" X="58402" Y="10151" />
				<Coordinate Order="561" X="58604" Y="9712" />
				<Coordinate Order="562" X="58711" Y="8716" />
				<Coordinate Order="563" X="58379" Y="8360" />
				<Coordinate Order="564" X="58070" Y="8360" />
				<Coordinate Order="565" X="57904" Y="8823" />
				<Coordinate Order="566" X="57584" Y="9416" />
				<Coordinate Order="567" X="57288" Y="9949" />
				<Coordinate Order="568" X="57074" Y="10483" />
				<Coordinate Order="569" X="57050" Y="10993" />
				<Coordinate Order="570" X="56944" Y="11194" />
				<Coordinate Order="571" X="56956" Y="11514" />
				<Coordinate Order="572" X="57050" Y="11752" />
				<Coordinate Order="573" X="57228" Y="12167" />
				<Coordinate Order="574" X="57335" Y="12368" />
				<Coordinate Order="575" X="57513" Y="12273" />
				<Coordinate Order="576" X="57750" Y="12392" />
				<Coordinate Order="577" X="57821" Y="12558" />
				<Coordinate Order="578" X="57857" Y="12831" />
				<Coordinate Order="579" X="57845" Y="13080" />
				<Coordinate Order="580" X="57833" Y="13269" />
				<Coordinate Order="581" X="57762" Y="13602" />
				<Coordinate Order="582" X="57714" Y="13649" />
				<Coordinate Order="583" X="57560" Y="13602" />
				<Coordinate Order="584" X="57216" Y="13364" />
				<Coordinate Order="585" X="56695" Y="13139" />
				<Coordinate Order="586" X="55876" Y="12629" />
				<Coordinate Order="587" X="55805" Y="12558" />
				<Coordinate Order="588" X="55604" Y="12451" />
				<Coordinate Order="589" X="55177" Y="12238" />
				<Coordinate Order="590" X="54726" Y="12036" />
				<Coordinate Order="591" X="54311" Y="11763" />
				<Coordinate Order="592" X="53920" Y="11467" />
				<Coordinate Order="593" X="53517" Y="11182" />
				<Coordinate Order="594" X="53042" Y="11064" />
				<Coordinate Order="595" X="52544" Y="11076" />
				<Coordinate Order="596" X="52070" Y="11052" />
				<Coordinate Order="597" X="51596" Y="10957" />
				<Coordinate Order="598" X="51240" Y="10637" />
				<Coordinate Order="599" X="51050" Y="10186" />
				<Coordinate Order="600" X="50813" Y="9771" />
			</Coordinates>
</Annotation>
<Annotation Name="_0" Type="Polygon" PartOfGroup="_0" Color="#F4FA58">
			<Coordinates>
				<Coordinate Order="0" X="13593" Y="23929" />
				<Coordinate Order="1" X="13621" Y="24116" />
				<Coordinate Order="2" X="13639" Y="24297" />
				<Coordinate Order="3" X="13639" Y="24497" />
				<Coordinate Order="4" X="13625" Y="24679" />
				<Coordinate Order="5" X="13557" Y="24852" />
				<Coordinate Order="6" X="13498" Y="25024" />
				<Coordinate Order="7" X="13380" Y="25179" />
				<Coordinate Order="8" X="13225" Y="25292" />
				<Coordinate Order="9" X="13080" Y="25406" />
				<Coordinate Order="10" X="12985" Y="25569" />
				<Coordinate Order="11" X="12916" Y="25747" />
				<Coordinate Order="12" X="12898" Y="25928" />
				<Coordinate Order="13" X="12935" Y="26115" />
				<Coordinate Order="14" X="12985" Y="26296" />
				<Coordinate Order="15" X="13039" Y="26451" />
				<Coordinate Order="16" X="13121" Y="26623" />
				<Coordinate Order="17" X="13212" Y="26782" />
				<Coordinate Order="18" X="13357" Y="26896" />
				<Coordinate Order="19" X="13530" Y="26973" />
				<Coordinate Order="20" X="13666" Y="27110" />
				<Coordinate Order="21" X="13775" Y="27259" />
				<Coordinate Order="22" X="13830" Y="27441" />
				<Coordinate Order="23" X="13843" Y="27628" />
				<Coordinate Order="24" X="13861" Y="27823" />
				<Coordinate Order="25" X="13902" Y="28014" />
				<Coordinate Order="26" X="13966" Y="28191" />
				<Coordinate Order="27" X="14043" Y="28359" />
				<Coordinate Order="28" X="14098" Y="28536" />
				<Coordinate Order="29" X="14134" Y="28718" />
				<Coordinate Order="30" X="14161" Y="28900" />
				<Coordinate Order="31" X="14152" Y="29031" />
				<Coordinate Order="32" X="14225" Y="29209" />
				<Coordinate Order="33" X="14325" Y="29368" />
				<Coordinate Order="34" X="14398" Y="29540" />
				<Coordinate Order="35" X="14416" Y="29722" />
				<Coordinate Order="36" X="14334" Y="29890" />
				<Coordinate Order="37" X="14234" Y="30045" />
				<Coordinate Order="38" X="14143" Y="30208" />
				<Coordinate Order="39" X="14070" Y="30390" />
				<Coordinate Order="40" X="14025" Y="30576" />
				<Coordinate Order="41" X="14002" Y="30758" />
				<Coordinate Order="42" X="13998" Y="30940" />
				<Coordinate Order="43" X="13998" Y="31130" />
				<Coordinate Order="44" X="13993" Y="31448" />
				<Coordinate Order="45" X="14039" Y="31630" />
				<Coordinate Order="46" X="14089" Y="31807" />
				<Coordinate Order="47" X="14148" Y="31980" />
				<Coordinate Order="48" X="14225" Y="32148" />
				<Coordinate Order="49" X="14316" Y="32316" />
				<Coordinate Order="50" X="14411" Y="32484" />
				<Coordinate Order="51" X="14493" Y="32657" />
				<Coordinate Order="52" X="14570" Y="32825" />
				<Coordinate Order="53" X="14670" Y="32984" />
				<Coordinate Order="54" X="14775" Y="33148" />
				<Coordinate Order="55" X="14897" Y="33316" />
				<Coordinate Order="56" X="15006" Y="33466" />
				<Coordinate Order="57" X="15184" Y="33506" />
				<Coordinate Order="58" X="15356" Y="33443" />
				<Coordinate Order="59" X="15542" Y="33402" />
				<Coordinate Order="60" X="15706" Y="33493" />
				<Coordinate Order="61" X="15829" Y="33629" />
				<Coordinate Order="62" X="15924" Y="33788" />
				<Coordinate Order="63" X="15979" Y="33938" />
				<Coordinate Order="64" X="16033" Y="34120" />
				<Coordinate Order="65" X="16074" Y="34297" />
				<Coordinate Order="66" X="16097" Y="34479" />
				<Coordinate Order="67" X="16106" Y="34660" />
				<Coordinate Order="68" X="16088" Y="34847" />
				<Coordinate Order="69" X="16024" Y="35028" />
				<Coordinate Order="70" X="15938" Y="35192" />
				<Coordinate Order="71" X="15815" Y="35328" />
				<Coordinate Order="72" X="15674" Y="35451" />
				<Coordinate Order="73" X="15533" Y="35574" />
				<Coordinate Order="74" X="15397" Y="35714" />
				<Coordinate Order="75" X="15288" Y="35869" />
				<Coordinate Order="76" X="15215" Y="36042" />
				<Coordinate Order="77" X="15052" Y="36332" />
				<Coordinate Order="78" X="14988" Y="36505" />
				<Coordinate Order="79" X="14915" Y="36678" />
				<Coordinate Order="80" X="14829" Y="36850" />
				<Coordinate Order="81" X="14752" Y="37018" />
				<Coordinate Order="82" X="14661" Y="37191" />
				<Coordinate Order="83" X="14575" Y="37355" />
				<Coordinate Order="84" X="14488" Y="37518" />
				<Coordinate Order="85" X="14407" Y="37695" />
				<Coordinate Order="86" X="14348" Y="37868" />
				<Coordinate Order="87" X="14284" Y="38041" />
				<Coordinate Order="88" X="14193" Y="38200" />
				<Coordinate Order="89" X="14116" Y="38368" />
				<Coordinate Order="90" X="13931" Y="38810" />
				<Coordinate Order="91" X="13743" Y="39088" />
				<Coordinate Order="92" X="13555" Y="39366" />
				<Coordinate Order="93" X="13375" Y="39643" />
				<Coordinate Order="94" X="13155" Y="39897" />
				<Coordinate Order="95" X="12885" Y="40093" />
				<Coordinate Order="96" X="12615" Y="40289" />
				<Coordinate Order="97" X="12338" Y="40477" />
				<Coordinate Order="98" X="12084" Y="40697" />
				<Coordinate Order="99" X="11880" Y="40959" />
				<Coordinate Order="100" X="11708" Y="41245" />
				<Coordinate Order="101" X="11561" Y="41547" />
				<Coordinate Order="102" X="11422" Y="41858" />
				<Coordinate Order="103" X="11284" Y="42160" />
				<Coordinate Order="104" X="11136" Y="42462" />
				<Coordinate Order="105" X="11030" Y="42569" />
				<Coordinate Order="106" X="11022" Y="42707" />
				<Coordinate Order="107" X="10949" Y="43042" />
				<Coordinate Order="108" X="10761" Y="43337" />
				<Coordinate Order="109" X="10687" Y="43663" />
				<Coordinate Order="110" X="10597" Y="43990" />
				<Coordinate Order="111" X="10499" Y="44309" />
				<Coordinate Order="112" X="10450" Y="44652" />
				<Coordinate Order="113" X="10458" Y="44987" />
				<Coordinate Order="114" X="10401" Y="45036" />
				<Coordinate Order="115" X="10254" Y="45346" />
				<Coordinate Order="116" X="10099" Y="45641" />
				<Coordinate Order="117" X="10148" Y="45967" />
				<Coordinate Order="118" X="9944" Y="46229" />
				<Coordinate Order="119" X="9739" Y="46490" />
				<Coordinate Order="120" X="9609" Y="46809" />
				<Coordinate Order="121" X="9576" Y="47136" />
				<Coordinate Order="122" X="9772" Y="47414" />
				<Coordinate Order="123" X="10074" Y="47569" />
				<Coordinate Order="124" X="10409" Y="47642" />
				<Coordinate Order="125" X="10581" Y="47928" />
				<Coordinate Order="126" X="10475" Y="48247" />
				<Coordinate Order="127" X="10393" Y="48566" />
				<Coordinate Order="128" X="10352" Y="48819" />
				<Coordinate Order="129" X="10091" Y="49031" />
				<Coordinate Order="130" X="9813" Y="48852" />
				<Coordinate Order="131" X="9543" Y="48656" />
				<Coordinate Order="132" X="9372" Y="48370" />
				<Coordinate Order="133" X="9225" Y="48075" />
				<Coordinate Order="134" X="9110" Y="47765" />
				<Coordinate Order="135" X="9069" Y="47438" />
				<Coordinate Order="136" X="9126" Y="47111" />
				<Coordinate Order="137" X="9249" Y="46621" />
				<Coordinate Order="138" X="9249" Y="46278" />
				<Coordinate Order="139" X="9265" Y="45935" />
				<Coordinate Order="140" X="9331" Y="45600" />
				<Coordinate Order="141" X="9429" Y="45273" />
				<Coordinate Order="142" X="9453" Y="44946" />
				<Coordinate Order="143" X="9306" Y="44644" />
				<Coordinate Order="144" X="9118" Y="44374" />
				<Coordinate Order="145" X="8988" Y="44072" />
				<Coordinate Order="146" X="8963" Y="43917" />
				<Coordinate Order="147" X="9061" Y="43582" />
				<Coordinate Order="148" X="9102" Y="43255" />
				<Coordinate Order="149" X="9184" Y="42920" />
				<Coordinate Order="150" X="9355" Y="42626" />
				<Coordinate Order="151" X="9519" Y="42340" />
				<Coordinate Order="152" X="9682" Y="42037" />
				<Coordinate Order="153" X="9805" Y="41727" />
				<Coordinate Order="154" X="9895" Y="41400" />
				<Coordinate Order="155" X="9993" Y="41065" />
				<Coordinate Order="156" X="10081" Y="40702" />
				<Coordinate Order="157" X="10202" Y="40400" />
				<Coordinate Order="158" X="10300" Y="40113" />
				<Coordinate Order="159" X="10467" Y="39840" />
				<Coordinate Order="160" X="10686" Y="39621" />
				<Coordinate Order="161" X="10928" Y="39417" />
				<Coordinate Order="162" X="11011" Y="39235" />
				<Coordinate Order="163" X="11147" Y="38955" />
				<Coordinate Order="164" X="11314" Y="38691" />
				<Coordinate Order="165" X="11435" Y="38403" />
				<Coordinate Order="166" X="11435" Y="38086" />
				<Coordinate Order="167" X="11450" Y="37776" />
				<Coordinate Order="168" X="11457" Y="37458" />
				<Coordinate Order="169" X="11518" Y="37148" />
				<Coordinate Order="170" X="11594" Y="36845" />
				<Coordinate Order="171" X="11662" Y="36543" />
				<Coordinate Order="172" X="11715" Y="36240" />
				<Coordinate Order="173" X="11730" Y="35938" />
				<Coordinate Order="174" X="11752" Y="35628" />
				<Coordinate Order="175" X="11798" Y="35310" />
				<Coordinate Order="176" X="11881" Y="35000" />
				<Coordinate Order="177" X="12002" Y="34720" />
				<Coordinate Order="178" X="12153" Y="34448" />
				<Coordinate Order="179" X="12312" Y="34168" />
				<Coordinate Order="180" X="12410" Y="33881" />
				<Coordinate Order="181" X="12486" Y="33578" />
				<Coordinate Order="182" X="12509" Y="33397" />
				<Coordinate Order="183" X="12433" Y="33102" />
				<Coordinate Order="184" X="12297" Y="32822" />
				<Coordinate Order="185" X="12305" Y="32520" />
				<Coordinate Order="186" X="12426" Y="32225" />
				<Coordinate Order="187" X="12509" Y="31922" />
				<Coordinate Order="188" X="12433" Y="31612" />
				<Coordinate Order="189" X="12320" Y="31317" />
				<Coordinate Order="190" X="12274" Y="31015" />
				<Coordinate Order="191" X="12373" Y="30712" />
				<Coordinate Order="192" X="12486" Y="30410" />
				<Coordinate Order="193" X="12350" Y="30394" />
				<Coordinate Order="194" X="12418" Y="30100" />
				<Coordinate Order="195" X="12562" Y="29820" />
				<Coordinate Order="196" X="12622" Y="29517" />
				<Coordinate Order="197" X="12562" Y="29215" />
				<Coordinate Order="198" X="12478" Y="28920" />
				<Coordinate Order="199" X="12441" Y="28617" />
				<Coordinate Order="200" X="12531" Y="28315" />
				<Coordinate Order="201" X="12562" Y="28012" />
				<Coordinate Order="202" X="12531" Y="27702" />
				<Coordinate Order="203" X="12509" Y="27400" />
				<Coordinate Order="204" X="12456" Y="27097" />
				<Coordinate Order="205" X="12395" Y="26779" />
				<Coordinate Order="206" X="12357" Y="26477" />
				<Coordinate Order="207" X="12312" Y="26174" />
				<Coordinate Order="208" X="12305" Y="25872" />
				<Coordinate Order="209" X="12403" Y="25569" />
				<Coordinate Order="210" X="12501" Y="25320" />
				<Coordinate Order="211" X="12577" Y="25017" />
				<Coordinate Order="212" X="12690" Y="24715" />
				<Coordinate Order="213" X="12879" Y="24473" />
				<Coordinate Order="214" X="13099" Y="24261" />
				<Coordinate Order="215" X="13325" Y="24049" />
			</Coordinates>
</Annotation>
<Annotation Name="_0" Type="Polygon" PartOfGroup="_0" Color="#F4FA58">
			<Coordinates>
				<Coordinate Order="0" X="49598" Y="50009" />
				<Coordinate Order="1" X="49510" Y="50420" />
				<Coordinate Order="2" X="49314" Y="50762" />
				<Coordinate Order="3" X="49079" Y="51085" />
				<Coordinate Order="4" X="48854" Y="51418" />
				<Coordinate Order="5" X="48629" Y="51741" />
				<Coordinate Order="6" X="48414" Y="52074" />
				<Coordinate Order="7" X="48022" Y="52133" />
				<Coordinate Order="8" X="47699" Y="52387" />
				<Coordinate Order="9" X="47562" Y="52759" />
				<Coordinate Order="10" X="47415" Y="53141" />
				<Coordinate Order="11" X="47210" Y="53483" />
				<Coordinate Order="12" X="46955" Y="53806" />
				<Coordinate Order="13" X="46642" Y="54051" />
				<Coordinate Order="14" X="46280" Y="54237" />
				<Coordinate Order="15" X="45957" Y="54472" />
				<Coordinate Order="16" X="45762" Y="54834" />
				<Coordinate Order="17" X="45517" Y="55147" />
				<Coordinate Order="18" X="45135" Y="55303" />
				<Coordinate Order="19" X="44744" Y="55323" />
				<Coordinate Order="20" X="44215" Y="55284" />
				<Coordinate Order="21" X="44284" Y="55137" />
				<Coordinate Order="22" X="44675" Y="55078" />
				<Coordinate Order="23" X="45057" Y="54941" />
				<Coordinate Order="24" X="45321" Y="54628" />
				<Coordinate Order="25" X="45507" Y="54266" />
				<Coordinate Order="26" X="45732" Y="53923" />
				<Coordinate Order="27" X="46045" Y="53669" />
				<Coordinate Order="28" X="46359" Y="53424" />
				<Coordinate Order="29" X="46711" Y="53238" />
				<Coordinate Order="30" X="47024" Y="52984" />
				<Coordinate Order="31" X="47239" Y="52641" />
				<Coordinate Order="32" X="47464" Y="52318" />
				<Coordinate Order="33" X="47768" Y="52064" />
				<Coordinate Order="34" X="48404" Y="51369" />
				<Coordinate Order="35" X="48727" Y="51134" />
				<Coordinate Order="36" X="49011" Y="50860" />
				<Coordinate Order="37" X="49197" Y="50508" />
				<Coordinate Order="38" X="49373" Y="50156" />
			</Coordinates>
</Annotation>
<Annotation Name="_0" Type="Polygon" PartOfGroup="_0" Color="#F4FA58">
			<Coordinates>
				<Coordinate Order="0" X="29496" Y="62956" />
				<Coordinate Order="1" X="29790" Y="63221" />
				<Coordinate Order="2" X="30181" Y="63230" />
				<Coordinate Order="3" X="30563" Y="63064" />
				<Coordinate Order="4" X="30915" Y="62878" />
				<Coordinate Order="5" X="31307" Y="62917" />
				<Coordinate Order="6" X="31620" Y="63181" />
				<Coordinate Order="7" X="31933" Y="63426" />
				<Coordinate Order="8" X="32286" Y="63622" />
				<Coordinate Order="9" X="32677" Y="63749" />
				<Coordinate Order="10" X="33068" Y="63818" />
				<Coordinate Order="11" X="33480" Y="63788" />
				<Coordinate Order="12" X="33891" Y="63700" />
				<Coordinate Order="13" X="34282" Y="63622" />
				<Coordinate Order="14" X="34673" Y="63651" />
				<Coordinate Order="15" X="35055" Y="63739" />
				<Coordinate Order="16" X="35466" Y="63769" />
				<Coordinate Order="17" X="35858" Y="63778" />
				<Coordinate Order="18" X="36239" Y="63681" />
				<Coordinate Order="19" X="36572" Y="63455" />
				<Coordinate Order="20" X="36846" Y="63152" />
				<Coordinate Order="21" X="37140" Y="62859" />
				<Coordinate Order="22" X="37228" Y="62712" />
				<Coordinate Order="23" X="37335" Y="62330" />
				<Coordinate Order="24" X="37658" Y="62076" />
				<Coordinate Order="25" X="38011" Y="61880" />
				<Coordinate Order="26" X="38383" Y="61743" />
				<Coordinate Order="27" X="38774" Y="61625" />
				<Coordinate Order="28" X="39146" Y="61498" />
				<Coordinate Order="29" X="39528" Y="61361" />
				<Coordinate Order="30" X="39909" Y="61205" />
				<Coordinate Order="31" X="40232" Y="60980" />
				<Coordinate Order="32" X="40330" Y="60598" />
				<Coordinate Order="33" X="40144" Y="60246" />
				<Coordinate Order="34" X="40125" Y="59844" />
				<Coordinate Order="35" X="40418" Y="59580" />
				<Coordinate Order="36" X="40770" Y="59404" />
				<Coordinate Order="37" X="40751" Y="59012" />
				<Coordinate Order="38" X="40947" Y="58670" />
				<Coordinate Order="39" X="41240" Y="58396" />
				<Coordinate Order="40" X="40868" Y="58552" />
				<Coordinate Order="41" X="40496" Y="58709" />
				<Coordinate Order="42" X="40115" Y="58836" />
				<Coordinate Order="43" X="39733" Y="58963" />
				<Coordinate Order="44" X="39351" Y="59120" />
				<Coordinate Order="45" X="38989" Y="59296" />
				<Coordinate Order="46" X="38627" Y="59453" />
				<Coordinate Order="47" X="38226" Y="59512" />
				<Coordinate Order="48" X="37815" Y="59560" />
				<Coordinate Order="49" X="37423" Y="59580" />
				<Coordinate Order="50" X="37022" Y="59649" />
				<Coordinate Order="51" X="36641" Y="59815" />
				<Coordinate Order="52" X="36288" Y="60001" />
				<Coordinate Order="53" X="35955" Y="60216" />
				<Coordinate Order="54" X="35633" Y="60451" />
				<Coordinate Order="55" X="35319" Y="60705" />
				<Coordinate Order="56" X="35036" Y="60980" />
				<Coordinate Order="57" X="34742" Y="61244" />
				<Coordinate Order="58" X="34380" Y="61420" />
				<Coordinate Order="59" X="33988" Y="61518" />
				<Coordinate Order="60" X="33597" Y="61576" />
				<Coordinate Order="61" X="33352" Y="61694" />
				<Coordinate Order="62" X="33000" Y="61880" />
				<Coordinate Order="63" X="32648" Y="62076" />
				<Coordinate Order="64" X="32286" Y="62232" />
				<Coordinate Order="65" X="31904" Y="62350" />
				<Coordinate Order="66" X="31493" Y="62389" />
				<Coordinate Order="67" X="31092" Y="62408" />
				<Coordinate Order="68" X="30700" Y="62467" />
				<Coordinate Order="69" X="30309" Y="62575" />
				<Coordinate Order="70" X="29937" Y="62702" />
				<Coordinate Order="71" X="29565" Y="62849" />
			</Coordinates>
</Annotation>
</Annotations>
	<AnnotationGroups>
		<Group Name="_0" PartOfGroup="_0" Color="#0000ff">
			<Attributes />
		</Group>
	</AnnotationGroups>
</ASAP_Annotations>
